[{"phelps":"BH01313NAM","text":"Nita Caje he woakisni mitawa, o mita Wakan Tanka, na ciksuye ki han he ookiye mitawa. Nikiyela ki han he awacin mitawa nahan tecihila ki han he mita kola. Wowaunsila Nitawa ki he le ounyan nahan ounyan iyokihe nupin ekta woakisni mitawa na wawokiye mitawa numwe. Tuwa Waoh’anpi Owas’in ki, Tuwa lyuha Waslolye ki, Tuwa lyuha.\n\n* Thy name is my healing, O my God, and remembrance of Thee is my remedy. Nearness to Thee is my hope, and love for Thee is my companion. Thy mercy to me is my healing and my succour in both this world and the world to come. Thou, verily, art the All-Bountiful, the All-Knowing, the All-Wise.","translations":[{"language":"af","lang_name":"Afrikaans"},{"language":"sq","lang_name":"Albanian"},{"language":"ar","lang_name":"Arabic"},{"language":"ar-translit","lang_name":"Arabic (Latin)"},{"language":"hy","lang_name":"Armenian"},{"language":"az","lang_name":"Azerbaijani"},{"language":"eu","lang_name":"Basque"},{"language":"bn","lang_name":"Bengali"},{"language":"bi","lang_name":"Bislama"},{"language":"bla","lang_name":"Blackfoot"},{"language":"bs","lang_name":"Bosnian"},{"language":"bg","lang_name":"Bulgarian"},{"language":"ca","lang_name":"Catalan"},{"language":"ceb","lang_name":"Cebuano"},{"language":"ch","lang_name":"Chamorro"},{"language":"ny","lang_name":"Chichewa"},{"language":"chn","lang_name":"Chinook Jargon"},{"language":"co","lang_name":"Corsican"},{"language":"hr","lang_name":"Croatian"},{"language":"cs","lang_name":"Czech"},{"language":"da","lang_name":"Danish"},{"language":"nl","lang_name":"Dutch"},{"language":"en","lang_name":"English"},{"language":"eo","lang_name":"Esperanto"},{"language":"et","lang_name":"Estonian"},{"language":"fo","lang_name":"Faroese"},{"language":"fj","lang_name":"Fijian"},{"language":"fi","lang_name":"Finnish"},{"language":"fr","lang_name":"French"},{"language":"lg","lang_name":"Ganda"},{"language":"de","lang_name":"German"},{"language":"ht","lang_name":"Haitian Creole"},{"language":"hur","lang_name":"Halkomelem"},{"language":"ha","lang_name":"Hausa"},{"language":"haw","lang_name":"Hawaiian"},{"language":"hz","lang_name":"Herero"},{"language":"hu","lang_name":"Hungarian"},{"language":"iba","lang_name":"Iban"},{"language":"is","lang_name":"Icelandic"},{"language":"id","lang_name":"Indonesian"},{"language":"ik","lang_name":"Inupiaq"},{"language":"it","lang_name":"Italian"},{"language":"ja","lang_name":"Japanese"},{"language":"kl","lang_name":"Kalaallisut"},{"language":"kn","lang_name":"Kannada"},{"language":"ky","lang_name":"Kirghiz"},{"language":"ko","lang_name":"Korean"},{"language":"lo","lang_name":"Lao"},{"language":"lv","lang_name":"Latvian"},{"language":"lt","lang_name":"Lithuanian"},{"language":"lb","lang_name":"Luxembourgish"},{"language":"mg","lang_name":"Malagasy"},{"language":"ms","lang_name":"Malay"},{"language":"ml","lang_name":"Malayalam"},{"language":"mt","lang_name":"Maltese"},{"language":"mi","lang_name":"Maori"},{"language":"moh","lang_name":"Mohawk"},{"language":"mn","lang_name":"Mongolian"},{"language":"cnr","lang_name":"Montenegrin"},{"language":"meu","lang_name":"Motu"},{"language":"nv","lang_name":"Navajo"},{"language":"ne","lang_name":"Nepali"},{"language":"no","lang_name":"Norwegian"},{"language":"fa","lang_name":"Persian"},{"language":"fa-translit","lang_name":"Persian (Latin)"},{"language":"pl","lang_name":"Polish"},{"language":"pt","lang_name":"Portuguese"},{"language":"ro","lang_name":"Romanian"},{"language":"ru","lang_name":"Russian"},{"language":"sr","lang_name":"Serbian"},{"language":"zh-Hans","lang_name":"Simplified Chinese"},{"language":"sk","lang_name":"Slovak"},{"language":"sl","lang_name":"Slovenian"},{"language":"st","lang_name":"Southern Sotho"},{"language":"es","lang_name":"Spanish"},{"language":"srn","lang_name":"Sranan Tongo"},{"language":"sw","lang_name":"Swahili"},{"language":"sv","lang_name":"Swedish"},{"language":"tl","lang_name":"Tagalog"},{"language":"ta","lang_name":"Tamil"},{"language":"th","lang_name":"Thai"},{"language":"tk","lang_name":"Turkmen"},{"language":"uk","lang_name":"Ukrainian"},{"language":"ur","lang_name":"Urdu"},{"language":"cy","lang_name":"Welsh"},{"language":"fy","lang_name":"Western Frisian"}]},{"phelps":"BH10505","text":"O mita Wakan Tanka! O mita Wakan tanka! Nita woyaka wicacante ki wica lucangleska nahan wokonze tanka nitawa ki wicayecipazo. Woahope Nitawa ki waanaguptanyan ikuseya iyapi nahan woope Nitawa ki ounyan yankapikte. O Waken Tanka, waeconpi kin han owicayakiyinkte, na wa-s aqwicayaye ca ilagnyoupikte. O Wakan Tanka!\nAwicalustanpiktesni, tka, Nita wooslolye oiyoyanpa ogna siowepi cankuwicayayinkte, naha Nita waunsila ogna cantepi ki wicaliokipi. Wawokiye naha Hancanyapi he Niye.\n\n* O my God! O my God! Unite the hearts of Thy servants, and reveal to them Thy great purpose. May they follow Thy commandments and abide in Thy law. Help them, O God, in their endeavour, and grant them strength to serve Thee.  O God! Leave them not to themselves, but guide their steps by the light of Thy knowledge, and cheer their hearts by Thy love. Verily, Thou art their helper and their Lord.","translations":[{"language":"af","lang_name":"Afrikaans"},{"language":"sq","lang_name":"Albanian"},{"language":"am","lang_name":"Amharic"},{"language":"hy","lang_name":"Armenian"},{"language":"bn","lang_name":"Bengali"},{"language":"bs","lang_name":"Bosnian"},{"language":"ch","lang_name":"Chamorro"},{"language":"chr","lang_name":"Cherokee"},{"language":"ny","lang_name":"Chichewa"},{"language":"chn","lang_name":"Chinook Jargon"},{"language":"co","lang_name":"Corsican"},{"language":"hr","lang_name":"Croatian"},{"language":"cs","lang_name":"Czech"},{"language":"da","lang_name":"Danish"},{"language":"nl","lang_name":"Dutch"},{"language":"en","lang_name":"English"},{"language":"eo","lang_name":"Esperanto"},{"language":"et","lang_name":"Estonian"},{"language":"fo","lang_name":"Faroese"},{"language":"fj","lang_name":"Fijian"},{"language":"fr","lang_name":"French"},{"language":"lg","lang_name":"Ganda"},{"language":"el","lang_name":"Greek"},{"language":"gu","lang_name":"Gujarati"},{"language":"ht","lang_name":"Haitian Creole"},{"language":"hur","lang_name":"Halkomelem"},{"language":"hz","lang_name":"Herero"},{"language":"hi","lang_name":"Hindi"},{"language":"hu","lang_name":"Hungarian"},{"language":"is","lang_name":"Icelandic"},{"language":"id","lang_name":"Indonesian"},{"language":"it","lang_name":"Italian"},{"language":"ja","lang_name":"Japanese"},{"language":"kl","lang_name":"Kalaallisut"},{"language":"kn","lang_name":"Kannada"},{"language":"ko","lang_name":"Korean"},{"language":"lv","lang_name":"Latvian"},{"language":"lb","lang_name":"Luxembourgish"},{"language":"ml","lang_name":"Malayalam"},{"language":"mt","lang_name":"Maltese"},{"language":"mi","lang_name":"Maori"},{"language":"mh","lang_name":"Marshallese"},{"language":"mic","lang_name":"Mikmaq"},{"language":"mn","lang_name":"Mongolian"},{"language":"meu","lang_name":"Motu"},{"language":"nv","lang_name":"Navajo"},{"language":"ne","lang_name":"Nepali"},{"language":"no","lang_name":"Norwegian"},{"language":"pap","lang_name":"Papiamento"},{"language":"pl","lang_name":"Polish"},{"language":"pt","lang_name":"Portuguese"},{"language":"ro","lang_name":"Romanian"},{"language":"sm","lang_name":"Samoan"},{"language":"zh-Hans","lang_name":"Simplified Chinese"},{"language":"sk","lang_name":"Slovak"},{"language":"sl","lang_name":"Slovenian"},{"language":"srn","lang_name":"Sranan Tongo"},{"language":"sw","lang_name":"Swahili"},{"language":"sv","lang_name":"Swedish"},{"language":"tl","lang_name":"Tagalog"},{"language":"ta","lang_name":"Tamil"},{"language":"te","lang_name":"Telugu"},{"language":"th","lang_name":"Thai"},{"language":"tpi","lang_name":"Tok Pisin"},{"language":"zh-Hant","lang_name":"Traditional Chinese"},{"language":"tk","lang_name":"Turkmen"},{"language":"tvl","lang_name":"Tuvalu"},{"language":"uk","lang_name":"Ukrainian"},{"language":"ur","lang_name":"Urdu"},{"language":"vi","lang_name":"Vietnamese"},{"language":"cy","lang_name":"Welsh"},{"language":"fy","lang_name":"Western Frisian"}]},{"phelps":"BH11209","text":"Waayantanin bluha\nWakantanka mitawa\nSloci in kta un makakaga\nNa ci yu onihan te\nLe oape ki el\nOmahiti ke sni\nNa niye onihitike\nWamahpa nica\nNa Niye winisica\nNisnala wakan ni tanka\nWokokipe el wayokiya\nNa iye oiciya\n\n\n* I bear witness, O my God, that Thou hast created me to know Thee and to worship Thee. I testify, at this moment, to my powerlessness and to Thy might, to my poverty and to Thy wealth.\nThere is none other God but Thee, the Help in Peril, the Self-Subsisting.","translations":[{"language":"af","lang_name":"Afrikaans"},{"language":"sq","lang_name":"Albanian"},{"language":"am","lang_name":"Amharic"},{"language":"ar","lang_name":"Arabic"},{"language":"ar-translit","lang_name":"Arabic (Latin)"},{"language":"az","lang_name":"Azerbaijani"},{"language":"be","lang_name":"Belarusian"},{"language":"bi","lang_name":"Bislama"},{"language":"bs","lang_name":"Bosnian"},{"language":"bg","lang_name":"Bulgarian"},{"language":"ca","lang_name":"Catalan"},{"language":"km","lang_name":"Central Khmer"},{"language":"ny","lang_name":"Chichewa"},{"language":"chn","lang_name":"Chinook Jargon"},{"language":"co","lang_name":"Corsican"},{"language":"cr","lang_name":"Cree"},{"language":"da","lang_name":"Danish"},{"language":"nl","lang_name":"Dutch"},{"language":"en","lang_name":"English"},{"language":"eo","lang_name":"Esperanto"},{"language":"fj","lang_name":"Fijian"},{"language":"fi","lang_name":"Finnish"},{"language":"fr","lang_name":"French"},{"language":"lg","lang_name":"Ganda"},{"language":"de","lang_name":"German"},{"language":"el","lang_name":"Greek"},{"language":"ht","lang_name":"Haitian Creole"},{"language":"hur","lang_name":"Halkomelem"},{"language":"haw","lang_name":"Hawaiian"},{"language":"hz","lang_name":"Herero"},{"language":"iba","lang_name":"Iban"},{"language":"is","lang_name":"Icelandic"},{"language":"id","lang_name":"Indonesian"},{"language":"ik","lang_name":"Inupiaq"},{"language":"it","lang_name":"Italian"},{"language":"ja","lang_name":"Japanese"},{"language":"kl","lang_name":"Kalaallisut"},{"language":"kn","lang_name":"Kannada"},{"language":"kiw","lang_name":"Kiwai"},{"language":"ko","lang_name":"Korean"},{"language":"lkt","lang_name":"Lakota"},{"language":"lv","lang_name":"Latvian"},{"language":"lt","lang_name":"Lithuanian"},{"language":"lb","lang_name":"Luxembourgish"},{"language":"mg","lang_name":"Malagasy"},{"language":"ml","lang_name":"Malayalam"},{"language":"mt","lang_name":"Maltese"},{"language":"mi","lang_name":"Maori"},{"language":"mh","lang_name":"Marshallese"},{"language":"moh","lang_name":"Mohawk"},{"language":"mn","lang_name":"Mongolian"},{"language":"meu","lang_name":"Motu"},{"language":"nv","lang_name":"Navajo"},{"language":"no","lang_name":"Norwegian"},{"language":"oj","lang_name":"Ojibwe"},{"language":"pap","lang_name":"Papiamento"},{"language":"fa","lang_name":"Persian"},{"language":"fa-translit","lang_name":"Persian (Latin)"},{"language":"pl","lang_name":"Polish"},{"language":"pt","lang_name":"Portuguese"},{"language":"pot","lang_name":"Potawatomi"},{"language":"ro","lang_name":"Romanian"},{"language":"ru","lang_name":"Russian"},{"language":"shs","lang_name":"Shuswap (Secwepemctsín)"},{"language":"sk","lang_name":"Slovak"},{"language":"srn","lang_name":"Sranan Tongo"},{"language":"sv","lang_name":"Swedish"},{"language":"tl","lang_name":"Tagalog"},{"language":"ta","lang_name":"Tamil"},{"language":"th","lang_name":"Thai"},{"language":"tk","lang_name":"Turkmen"},{"language":"tvl","lang_name":"Tuvalu"},{"language":"ur","lang_name":"Urdu"},{"language":"fy","lang_name":"Western Frisian"}]}]
