[{"phelps":"AB10701","text":"O Iroij! Komman bwe ajri rein ren menin edrok ko reweppen. Komman bwe ren edrok im wonmanlok ilo jikin kallib in Bujen eo Am, im lelok nan ir mour kaal im aibuijuij jen dren ko rej wotlok tok jen koro ko ilo Abha Kingdom.\n\nO Kwe Iroij in jouij! Na ij juon ajri edrik wot, kautiej io ilo ao drelon waj ilo ailin eo. Na armij in lalin, komman bwe in bok mour in lan; na ij jen lalin, komman bwe in bed ilo jikin eo ilan; dri jerata, komman bwe in romak lok; na menin komanman wot, letok jitob ioo, im komman bwe in kokkalen menin jeramon ko Am ejelok jemlokier.\n\nKwe Kwokajur, Eo eobrak kin yokwe.","category":"AJRI IM JODRIKDRIK","order_in_cat":1,"source":"bahaiprayers.net","version":"fb281a87-644d-4bdd-93d8-b1c18f993f64","translations":[{"language":"sq","lang_name":"Albanian"},{"language":"hy","lang_name":"Armenian"},{"language":"bs","lang_name":"Bosnian"},{"language":"bg","lang_name":"Bulgarian"},{"language":"ca","lang_name":"Catalan"},{"language":"da","lang_name":"Danish"},{"language":"nl","lang_name":"Dutch"},{"language":"en","lang_name":"English"},{"language":"eo","lang_name":"Esperanto"},{"language":"de","lang_name":"German"},{"language":"el","lang_name":"Greek"},{"language":"gu","lang_name":"Gujarati"},{"language":"ht","lang_name":"Haitian Creole"},{"language":"iba","lang_name":"Iban"},{"language":"it","lang_name":"Italian"},{"language":"ja","lang_name":"Japanese"},{"language":"kn","lang_name":"Kannada"},{"language":"lo","lang_name":"Lao"},{"language":"lv","lang_name":"Latvian"},{"language":"lb","lang_name":"Luxembourgish"},{"language":"ml","lang_name":"Malayalam"},{"language":"mi","lang_name":"Maori"},{"language":"meu","lang_name":"Motu"},{"language":"ne","lang_name":"Nepali"},{"language":"fa","lang_name":"Persian"},{"language":"fa-translit","lang_name":"Persian (Latin)"},{"language":"pl","lang_name":"Polish"},{"language":"ro","lang_name":"Romanian"},{"language":"sm","lang_name":"Samoan"},{"language":"zh-Hans","lang_name":"Simplified Chinese"},{"language":"sk","lang_name":"Slovak"},{"language":"st","lang_name":"Southern Sotho"},{"language":"es","lang_name":"Spanish"},{"language":"sv","lang_name":"Swedish"},{"language":"tl","lang_name":"Tagalog"},{"language":"ta","lang_name":"Tamil"},{"language":"th","lang_name":"Thai"},{"language":"zh-Hant","lang_name":"Traditional Chinese"},{"language":"uk","lang_name":"Ukrainian"},{"language":"ur","lang_name":"Urdu"},{"language":"cy","lang_name":"Welsh"}]},{"phelps":"ABU0129EDU","text":"O Anij! Kojelalokjen ajri rein. Ajri rein rej ine in jikin kallib in wijki eo Am, ut ko ilo melaj eo Am, rose ko in jikin kallib eo Am. Komman bwe Am wit en wotlok ioier, komman bwe Al in Mol eo en romak ioier kin yokwe eo Am.\n\nKomman bwe Kituom en kemourur ir bwe ren maron katak, edrok im wonmanlok im bed ilo aibujuij otem aibuijuij. Kwe Dri letok. Kwe Dri tiriamo.","category":"AJRI IM JODRIKDRIK","order_in_cat":2,"source":"bahaiprayers.net","version":"a5361100-44f6-4c1a-870d-fcb5c25a6fb7","translations":[{"language":"af","lang_name":"Afrikaans"},{"language":"sq","lang_name":"Albanian"},{"language":"hy","lang_name":"Armenian"},{"language":"az","lang_name":"Azerbaijani"},{"language":"eu","lang_name":"Basque"},{"language":"bi","lang_name":"Bislama"},{"language":"bs","lang_name":"Bosnian"},{"language":"bg","lang_name":"Bulgarian"},{"language":"ceb","lang_name":"Cebuano"},{"language":"ch","lang_name":"Chamorro"},{"language":"co","lang_name":"Corsican"},{"language":"da","lang_name":"Danish"},{"language":"nl","lang_name":"Dutch"},{"language":"en","lang_name":"English"},{"language":"eo","lang_name":"Esperanto"},{"language":"et","lang_name":"Estonian"},{"language":"fo","lang_name":"Faroese"},{"language":"fi","lang_name":"Finnish"},{"language":"fr","lang_name":"French"},{"language":"lg","lang_name":"Ganda"},{"language":"de","lang_name":"German"},{"language":"gil","lang_name":"Gilbertese"},{"language":"el","lang_name":"Greek"},{"language":"ht","lang_name":"Haitian Creole"},{"language":"haw","lang_name":"Hawaiian"},{"language":"hz","lang_name":"Herero"},{"language":"hu","lang_name":"Hungarian"},{"language":"is","lang_name":"Icelandic"},{"language":"it","lang_name":"Italian"},{"language":"kl","lang_name":"Kalaallisut"},{"language":"kn","lang_name":"Kannada"},{"language":"ky","lang_name":"Kirghiz"},{"language":"lv","lang_name":"Latvian"},{"language":"mg","lang_name":"Malagasy"},{"language":"mr","lang_name":"Marathi"},{"language":"mn","lang_name":"Mongolian"},{"language":"cnr","lang_name":"Montenegrin"},{"language":"nal","lang_name":"Nalik"},{"language":"no","lang_name":"Norwegian"},{"language":"kj","lang_name":"Oshikwanyama"},{"language":"pap","lang_name":"Papiamento"},{"language":"fa","lang_name":"Persian"},{"language":"fa-translit","lang_name":"Persian (Latin)"},{"language":"pl","lang_name":"Polish"},{"language":"pt","lang_name":"Portuguese"},{"language":"ro","lang_name":"Romanian"},{"language":"diu","lang_name":"Rugciriku"},{"language":"se","lang_name":"Sami"},{"language":"sm","lang_name":"Samoan"},{"language":"sk","lang_name":"Slovak"},{"language":"st","lang_name":"Southern Sotho"},{"language":"es","lang_name":"Spanish"},{"language":"sv","lang_name":"Swedish"},{"language":"tl","lang_name":"Tagalog"},{"language":"ta","lang_name":"Tamil"},{"language":"te","lang_name":"Telugu"},{"language":"tet","lang_name":"Tetum"},{"language":"tpi","lang_name":"Tok Pisin"},{"language":"zh-Hant","lang_name":"Traditional Chinese"},{"language":"uk","lang_name":"Ukrainian"},{"language":"cy","lang_name":"Welsh"}]},{"phelps":"ABU0009SER","text":"O Kwe Iroij in jouij, Kwe Eo Kwojouij im maron! Kimij Drijilkam im emoj am koonwaj im bed iumin kejbarok eo Am. Kalimjek kim kin Mejam ejouij. Koromak mej ko mejam, karonlokjen lojilinim, im letok jelalokjen im yokwe nan buruom. Komman bwe jitob ko am ren monono im lanlin kin naan ko Am. O Iroij! kalikar nan kim ial eo nan ailin eo Am im kemour kim kin menwan Jitob Kwojarjar. Kejramon kin mour indreo im letok nan kim utiej eo ejelok jemlokin. Kobaik armij otemjij im kemram lok lalin an armij. Komman bwe kimin lor ial eo Am, kijorore tok ainemon eo Am im kabukot menin ittino ko ilo ailin eo Am. O Anij! Kobaik kimwoj im kobaik burom kin juon kotan eo eban jako. Emol, Kwe Dri letok, Kwe Dri jouij im Kwe Dri Maron tata.","category":"ARMIJ OTEMJIJ","cat_order":1,"order_in_cat":1,"source":"bahaiprayers.net","version":"389dfe98-668c-4e28-a825-bc889dfe47b3","translations":[{"language":"af","lang_name":"Afrikaans"},{"language":"ar","lang_name":"Arabic"},{"language":"ar-translit","lang_name":"Arabic (Latin)"},{"language":"az","lang_name":"Azerbaijani"},{"language":"bs","lang_name":"Bosnian"},{"language":"bg","lang_name":"Bulgarian"},{"language":"ca","lang_name":"Catalan"},{"language":"ch","lang_name":"Chamorro"},{"language":"nl","lang_name":"Dutch"},{"language":"en","lang_name":"English"},{"language":"eo","lang_name":"Esperanto"},{"language":"fr","lang_name":"French"},{"language":"lg","lang_name":"Ganda"},{"language":"de","lang_name":"German"},{"language":"el","lang_name":"Greek"},{"language":"ht","lang_name":"Haitian Creole"},{"language":"hu","lang_name":"Hungarian"},{"language":"is","lang_name":"Icelandic"},{"language":"id","lang_name":"Indonesian"},{"language":"it","lang_name":"Italian"},{"language":"lv","lang_name":"Latvian"},{"language":"ml","lang_name":"Malayalam"},{"language":"mt","lang_name":"Maltese"},{"language":"ne","lang_name":"Nepali"},{"language":"no","lang_name":"Norwegian"},{"language":"fa","lang_name":"Persian"},{"language":"fa-translit","lang_name":"Persian (Latin)"},{"language":"pl","lang_name":"Polish"},{"language":"pt","lang_name":"Portuguese"},{"language":"ro","lang_name":"Romanian"},{"language":"ru","lang_name":"Russian"},{"language":"st","lang_name":"Southern Sotho"},{"language":"es","lang_name":"Spanish"},{"language":"tl","lang_name":"Tagalog"},{"language":"vi","lang_name":"Vietnamese"},{"language":"cy","lang_name":"Welsh"}]},{"phelps":"BB00018FOR","text":"## BAMLE \n*(FAMILY)\n\nIj oware jolok bwid eo Am, O ao Anij, im kajitok kin jolok bwid ilo wewen eo Kwoknan bwe dri jerbal ro Am ren jede Ibbam kake. Ij oware Yuk bwe Kwon jeerlok jerawiwi ko am ekkar nan Am Iroij, im jolok ao bwid, an jino im jema, im ro ilo lomnak eo Am bwe emoj air drelone waj imon yokwe eo Am ilo wewen eo ejejet im ekkar nan Kajur potata eo Am ellalok jen men otemjij im ejjejet nan aibuijuij in Kajur eo Am ilan.\n\nO ao Anij! Emoj Am kakajur jitob eo ao bwe en kajitok jiban jen Yuk, ejelok bar juon inaj kir nane ijelokin wot Kwe. Kwo utiej im aibuijuij; ij nebar Yuk toon wot Am kallikar Yuk nan io, im oware Yuk bwe Kwon jolok ao bwid, einwot ke iar likjab jen ao jela kin Yuk, im jab etetal ilo ial in yokwe eo Am.","category":"BAMLE","cat_order":2,"order_in_cat":1,"source":"bahaiprayers.net","version":"3cf64491-99bb-422c-a680-72ab101ce222","translations":[{"language":"ar","lang_name":"Arabic"},{"language":"ar-translit","lang_name":"Arabic (Latin)"},{"language":"az","lang_name":"Azerbaijani"},{"language":"sne","lang_name":"Bau Bidayuh"},{"language":"bs","lang_name":"Bosnian"},{"language":"bg","lang_name":"Bulgarian"},{"language":"ca","lang_name":"Catalan"},{"language":"da","lang_name":"Danish"},{"language":"nl","lang_name":"Dutch"},{"language":"en","lang_name":"English"},{"language":"et","lang_name":"Estonian"},{"language":"fr","lang_name":"French"},{"language":"de","lang_name":"German"},{"language":"el","lang_name":"Greek"},{"language":"is","lang_name":"Icelandic"},{"language":"kl","lang_name":"Kalaallisut"},{"language":"kn","lang_name":"Kannada"},{"language":"mt","lang_name":"Maltese"},{"language":"fa","lang_name":"Persian"},{"language":"fa-translit","lang_name":"Persian (Latin)"},{"language":"pl","lang_name":"Polish"},{"language":"pt","lang_name":"Portuguese"},{"language":"ro","lang_name":"Romanian"},{"language":"ru","lang_name":"Russian"},{"language":"es","lang_name":"Spanish"},{"language":"tl","lang_name":"Tagalog"},{"language":"ta","lang_name":"Tamil"}]},{"phelps":"BB00617","text":"Ij oware jolok bwid eo Am, O ao Anij, im kajitok kin jolok bwid ilo wewen eo Kwoknan bwe dri jerbal ro Am ren jede Ibbam kake. Ij oware Yuk bwe Kwon jeerlok jerawiwi ko am ekkar nan Am Iroij, im jolok ao bwid, an jino im jema, im ro ilo lomnak eo Am bwe emoj air drelone waj imon yokwe eo Am ilo wewen eo ejejet im ekkar nan Kajur potata eo Am ellalok jen men otemjij im ejjejet nan aibuijuij in Kajur eo Am ilan.\n\nO ao Anij! Emoj Am kakajur jitob eo ao bwe en kajitok jiban jen Yuk, ejelok bar juon inaj kir nane ijelokin wot Kwe. Kwo utiej im aibuijuij; ij nebar Yuk toon wot Am kallikar Yuk nan io, im oware Yuk bwe Kwon jolok ao bwid, einwot ke iar likjab jen ao jela kin Yuk, im jab etetal ilo ial in yokwe eo Am.","category":"BAMLE","cat_order":2,"order_in_cat":2,"source":"bahaiprayers.net","version":"fb6959c2-ea64-45ea-b638-ea0100c1f078","translations":[{"language":"sq","lang_name":"Albanian"},{"language":"hy","lang_name":"Armenian"},{"language":"az","lang_name":"Azerbaijani"},{"language":"sne","lang_name":"Bau Bidayuh"},{"language":"bs","lang_name":"Bosnian"},{"language":"bg","lang_name":"Bulgarian"},{"language":"ca","lang_name":"Catalan"},{"language":"hr","lang_name":"Croatian"},{"language":"cs","lang_name":"Czech"},{"language":"da","lang_name":"Danish"},{"language":"nl","lang_name":"Dutch"},{"language":"en","lang_name":"English"},{"language":"et","lang_name":"Estonian"},{"language":"fi","lang_name":"Finnish"},{"language":"fr","lang_name":"French"},{"language":"lg","lang_name":"Ganda"},{"language":"de","lang_name":"German"},{"language":"gux","lang_name":"Gourmanchéma"},{"language":"el","lang_name":"Greek"},{"language":"gu","lang_name":"Gujarati"},{"language":"ht","lang_name":"Haitian Creole"},{"language":"hz","lang_name":"Herero"},{"language":"hu","lang_name":"Hungarian"},{"language":"iba","lang_name":"Iban"},{"language":"is","lang_name":"Icelandic"},{"language":"id","lang_name":"Indonesian"},{"language":"it","lang_name":"Italian"},{"language":"kl","lang_name":"Kalaallisut"},{"language":"kn","lang_name":"Kannada"},{"language":"ky","lang_name":"Kirghiz"},{"language":"ko","lang_name":"Korean"},{"language":"lb","lang_name":"Luxembourgish"},{"language":"mg","lang_name":"Malagasy"},{"language":"ml","lang_name":"Malayalam"},{"language":"mt","lang_name":"Maltese"},{"language":"ne","lang_name":"Nepali"},{"language":"kj","lang_name":"Oshikwanyama"},{"language":"pl","lang_name":"Polish"},{"language":"pt","lang_name":"Portuguese"},{"language":"ro","lang_name":"Romanian"},{"language":"diu","lang_name":"Rugciriku"},{"language":"ru","lang_name":"Russian"},{"language":"zh-Hans","lang_name":"Simplified Chinese"},{"language":"sk","lang_name":"Slovak"},{"language":"es","lang_name":"Spanish"},{"language":"tl","lang_name":"Tagalog"},{"language":"ta","lang_name":"Tamil"},{"language":"tet","lang_name":"Tetum"},{"language":"zh-Hant","lang_name":"Traditional Chinese"},{"language":"tk","lang_name":"Turkmen"},{"language":"tvl","lang_name":"Tuvalu"},{"language":"uk","lang_name":"Ukrainian"}]},{"phelps":"AB06211","text":"Kabin bunten ne ko neem, O Iroij, ilo ial eo Am im kakajur buruem ilo am kibilie nan Kwe. Ukot waj mej ko mejem nan aibuijuij in juon-wot eo Am, im kamononoik einbwinim kin kokkalen juon-wot eo Am jen lan. Kebelbel enbwinim kin nuknuk in jouij eo Am, im jolok jen mejem men ko rej binej kin jerawiwi, im letok nan kim kab in jouij eo Am; bwe aurok ilo aolep men in komanman ren al im nebar Yuk iman utiej im kajur eo Am. Innem Kwon kalikar Yuk, O Iroij, kin tiriamo in naan eo Am im itino in bed eo Am, im bwe kin jar eo ekwojarjar en kokajur jitob ko am— juon jar eo emoj an le ilonin naan ko im leta ko im ellalok ilonin ainikien syllable ko im ainikien ko—bwe aolep men otemjij ren onlok im ejelok mokta jen an walok meram eo Am.\n\nIroij! Errein dri jerbal ro rej bed wot ilo air bin ilo Bujen im Kallimur eo Am, im rej jirok bin ilo air drebij katak eo Am im rebij torerein nuknuk in kajur im utiej eo Am. Jiban ir, O Iroij, kin jouij eo Am im kabin ir kin kajur eo Am im kakajur ir ilo air kiblie nan Kwe.\n\nKwe Dri jolok bwid im Dri jouij.","category":"BIN ILO BUJEN EO","cat_order":3,"order_in_cat":1,"source":"bahaiprayers.net","version":"a0c3cc0a-b9fb-4a00-a684-91019d0a7ed0","translations":[{"language":"af","lang_name":"Afrikaans"},{"language":"sq","lang_name":"Albanian"},{"language":"ar","lang_name":"Arabic"},{"language":"ar-translit","lang_name":"Arabic (Latin)"},{"language":"az","lang_name":"Azerbaijani"},{"language":"bs","lang_name":"Bosnian"},{"language":"bg","lang_name":"Bulgarian"},{"language":"ca","lang_name":"Catalan"},{"language":"hr","lang_name":"Croatian"},{"language":"da","lang_name":"Danish"},{"language":"nl","lang_name":"Dutch"},{"language":"en","lang_name":"English"},{"language":"fo","lang_name":"Faroese"},{"language":"fj","lang_name":"Fijian"},{"language":"fr","lang_name":"French"},{"language":"de","lang_name":"German"},{"language":"el","lang_name":"Greek"},{"language":"hu","lang_name":"Hungarian"},{"language":"iba","lang_name":"Iban"},{"language":"is","lang_name":"Icelandic"},{"language":"id","lang_name":"Indonesian"},{"language":"ik","lang_name":"Inupiaq"},{"language":"it","lang_name":"Italian"},{"language":"ja","lang_name":"Japanese"},{"language":"ko","lang_name":"Korean"},{"language":"ml","lang_name":"Malayalam"},{"language":"mi","lang_name":"Maori"},{"language":"no","lang_name":"Norwegian"},{"language":"pl","lang_name":"Polish"},{"language":"pt","lang_name":"Portuguese"},{"language":"sk","lang_name":"Slovak"},{"language":"st","lang_name":"Southern Sotho"},{"language":"es","lang_name":"Spanish"},{"language":"sv","lang_name":"Swedish"},{"language":"tl","lang_name":"Tagalog"},{"language":"uk","lang_name":"Ukrainian"}]},{"phelps":"AB02342AWA","text":"O Anij in tiriamo! Lewoj kamolol nan Kwe bwe Kwar karuj im kemour io. Emoj am letok meja bwe in lolokjen im letok lojilnu bwe in ronlokjen, im tel io nan ailin eo Am im kwalok nan io ial eo Am. Emoj Am kwalok nan io ial eo ejimwe im komman bwe in drelone wan lomor eo. O Anij! Komman bwe in bin im kajur. Kejbarok io jen melejon ko rekajur im kejbarok im wonake io ilo jikin likibejnak ilo Bujen im Kallimur eo Am. Kwe Dri lolokjen. Kwe Dri ronjake.\n\nO Kwe Anij in tiriamo. Letok nan io juon buru eo im, einwot juon kilaj, emaron romak kin meram in yokwe eo Am, im likit ioo lomnak ko romman renaj ukot lalin nan juon jikin kallib in rose kin tor tok in kejramon ko jen lan.\n\nKwoj Dri yokwe, Dri tiriamo. Kwe Anij in letok jeramon elab.","category":"BIN ILO BUJEN EO","cat_order":3,"order_in_cat":2,"source":"bahaiprayers.net","version":"6d5b2c2a-81ea-4844-bb93-d7fef25cbc16","translations":[{"language":"af","lang_name":"Afrikaans"},{"language":"sq","lang_name":"Albanian"},{"language":"ar","lang_name":"Arabic"},{"language":"ar-translit","lang_name":"Arabic (Latin)"},{"language":"az","lang_name":"Azerbaijani"},{"language":"bn","lang_name":"Bengali"},{"language":"bg","lang_name":"Bulgarian"},{"language":"ca","lang_name":"Catalan"},{"language":"da","lang_name":"Danish"},{"language":"nl","lang_name":"Dutch"},{"language":"en","lang_name":"English"},{"language":"eo","lang_name":"Esperanto"},{"language":"fr","lang_name":"French"},{"language":"lg","lang_name":"Ganda"},{"language":"el","lang_name":"Greek"},{"language":"is","lang_name":"Icelandic"},{"language":"it","lang_name":"Italian"},{"language":"lv","lang_name":"Latvian"},{"language":"mg","lang_name":"Malagasy"},{"language":"pl","lang_name":"Polish"},{"language":"pt","lang_name":"Portuguese"},{"language":"ro","lang_name":"Romanian"},{"language":"ru","lang_name":"Russian"},{"language":"sk","lang_name":"Slovak"},{"language":"es","lang_name":"Spanish"},{"language":"sv","lang_name":"Swedish"},{"language":"tl","lang_name":"Tagalog"},{"language":"zh-Hant","lang_name":"Traditional Chinese"},{"language":"fy","lang_name":"Western Frisian"}]},{"phelps":"BH09289","text":"Jiban io, O ao Anij, bwe in bed ebake Yuk, im jokwe iloan melan ko ilo oror eo Am, bwe ilo ao etolok jen Kwe ekkoman bwe ao en maron jako. Komman bwe in bed im kakije ilo ailurlur in ba ko bein tiriamo eo Am, bwe kijeek in ao jenelok jen Kwe emoj an tile im kaonlok buruo. Kebak waj io nan river in mour, bwe ao eurur kin an maro im jab kakije in bukot Yuk. Ao jan, O ao Anij, ej kwalok kin jonan an buruo entan im buromoj, im drenin kemjalal retorlok jen meja ilo ao kwalok jonan yokwe eo ao nan Yuk.\n\nIj owar Yuk, kin nebar eo Kwoj nebar Yuk kake im kin aibuijuij eo Kwoj kaibuijuij aurok eo Am make kake, komman bwe kemin mottan ro otemjij im emoj air kile Yuk im kamol kajur im utiej potata eo Am ilo ran ko Am. Jiban kim bwe kemin idrak, O ao Anij, jen adin bein tiriamo dren ko drenin jouij im yokwe eo Am, bwe kemin maron meloklok jabrewot ak Kwe wot, im boub wot kin Kwe. Kwo-kajur nan komman ta eo Kwo-konan. Ebar ejelok Anij Ijelokim, Dri maron, Dri Jiban ilo ien ban, Eo ej bed kin E make.\n\nEaibuijuij Etam, O Kwe eo Kwoj King in king ro otemjij.","category":"ELLOK JEN MEN KO AN MOUR IN","cat_order":4,"order_in_cat":1,"source":"bahaiprayers.net","version":"f96fd059-107e-4c38-8762-c61b4bd77bd6","translations":[{"language":"af","lang_name":"Afrikaans"},{"language":"az","lang_name":"Azerbaijani"},{"language":"sne","lang_name":"Bau Bidayuh"},{"language":"bg","lang_name":"Bulgarian"},{"language":"ca","lang_name":"Catalan"},{"language":"da","lang_name":"Danish"},{"language":"nl","lang_name":"Dutch"},{"language":"en","lang_name":"English"},{"language":"fi","lang_name":"Finnish"},{"language":"fr","lang_name":"French"},{"language":"de","lang_name":"German"},{"language":"el","lang_name":"Greek"},{"language":"ht","lang_name":"Haitian Creole"},{"language":"hu","lang_name":"Hungarian"},{"language":"is","lang_name":"Icelandic"},{"language":"id","lang_name":"Indonesian"},{"language":"it","lang_name":"Italian"},{"language":"ky","lang_name":"Kirghiz"},{"language":"lv","lang_name":"Latvian"},{"language":"lb","lang_name":"Luxembourgish"},{"language":"ml","lang_name":"Malayalam"},{"language":"pl","lang_name":"Polish"},{"language":"pt","lang_name":"Portuguese"},{"language":"ro","lang_name":"Romanian"},{"language":"ru","lang_name":"Russian"},{"language":"se","lang_name":"Sami"},{"language":"sm","lang_name":"Samoan"},{"language":"sk","lang_name":"Slovak"},{"language":"es","lang_name":"Spanish"},{"language":"tl","lang_name":"Tagalog"},{"language":"tvl","lang_name":"Tuvalu"},{"language":"uk","lang_name":"Ukrainian"}]},{"phelps":"BB00522","text":"O Iroij! Ilo Kwe ij bukot kejbarok eo Am, im nan aolepen kokkale ko Am ij aje waj buruo.\n\nO Iroij! Mekarta ilo ien ao itoitak ak ilo ao bed ijo jiku, im ilo ao boub ak ilo ao jerbal, ij likit aolepen ao like ilo Kwe.\n\nLetok nan io bareinwot jiban eo Am elab bwe in maron mour im anemkoj jen jabrewot, O Kwe Eo ejelok jonan Am tiriamo!\n\nLetok nan io kij eo ao, O Iroij, ekkar nan Am konan, im komman bwe en bo buruo kin jabrewot men otemjij emoj Am karok nan io.\n\nAolep maron rej Am ekkar nan Ankilam.","category":"ELLOK JEN MEN KO AN MOUR IN","cat_order":4,"order_in_cat":2,"source":"bahaiprayers.net","version":"1c4fced0-2b9d-498a-aad3-08f52146a5f1","translations":[{"language":"sq","lang_name":"Albanian"},{"language":"hy","lang_name":"Armenian"},{"language":"az","lang_name":"Azerbaijani"},{"language":"sne","lang_name":"Bau Bidayuh"},{"language":"bs","lang_name":"Bosnian"},{"language":"bg","lang_name":"Bulgarian"},{"language":"ca","lang_name":"Catalan"},{"language":"ceb","lang_name":"Cebuano"},{"language":"cs","lang_name":"Czech"},{"language":"da","lang_name":"Danish"},{"language":"nl","lang_name":"Dutch"},{"language":"en","lang_name":"English"},{"language":"et","lang_name":"Estonian"},{"language":"fi","lang_name":"Finnish"},{"language":"fr","lang_name":"French"},{"language":"de","lang_name":"German"},{"language":"el","lang_name":"Greek"},{"language":"ht","lang_name":"Haitian Creole"},{"language":"hz","lang_name":"Herero"},{"language":"iba","lang_name":"Iban"},{"language":"is","lang_name":"Icelandic"},{"language":"it","lang_name":"Italian"},{"language":"lv","lang_name":"Latvian"},{"language":"lb","lang_name":"Luxembourgish"},{"language":"mt","lang_name":"Maltese"},{"language":"pl","lang_name":"Polish"},{"language":"pt","lang_name":"Portuguese"},{"language":"ro","lang_name":"Romanian"},{"language":"ru","lang_name":"Russian"},{"language":"sm","lang_name":"Samoan"},{"language":"sk","lang_name":"Slovak"},{"language":"sl","lang_name":"Slovenian"},{"language":"es","lang_name":"Spanish"},{"language":"sv","lang_name":"Swedish"},{"language":"tl","lang_name":"Tagalog"},{"language":"ta","lang_name":"Tamil"},{"language":"zh-Hant","lang_name":"Traditional Chinese"},{"language":"tvl","lang_name":"Tuvalu"},{"language":"vi","lang_name":"Vietnamese"}]},{"phelps":"AB04980HOP","text":"O Anij, ao Anij! Kwoj ao Kejatdrikdrik im ao Jitenburu, ao Kotobar eo Eutiej tata im ao Konan! Ilo etta im buru emol ij jar nan Yuk bwe Kwon likit io bwe in juon kokkalen yokwe eo Am eutiej ilo lal eo Am, juon lamp in jelalokjen eo Am ilubiljin menin komanman ko Am, im juon flag in jeramon eo ekwojarjar ilo ailin eo Am.\n\nKobaik waj io ibben dri jerbal ro Am im emoj air kojenlok ir jen men otemjij ak Kwe wot, emoj air kareoik ir jen men wan ko an lalin, im emoj air rolok jen ainikien kabo im lomnak ko rewan.\n\nKomman bwe buruo en obrak kin monono jen jitob in kejramon jen ailin eo Am, im keromak lok meja nan ao loe dri jiban ro rejab mwijkok air wonlaltak jen ailin kajur im aibuijuij potata eo Am.\n\nKwe, ilo mol, Kwokajur potata, Kwoaibuijuij potata im Kwokajur otem kajur.","category":"ELLOK JEN MEN KO AN MOUR IN","cat_order":4,"order_in_cat":3,"source":"bahaiprayers.net","version":"e1fdbb5c-08ba-499a-af18-cf01a2dc8818","translations":[{"language":"sq","lang_name":"Albanian"},{"language":"hy","lang_name":"Armenian"},{"language":"az","lang_name":"Azerbaijani"},{"language":"bn","lang_name":"Bengali"},{"language":"bg","lang_name":"Bulgarian"},{"language":"ca","lang_name":"Catalan"},{"language":"da","lang_name":"Danish"},{"language":"nl","lang_name":"Dutch"},{"language":"en","lang_name":"English"},{"language":"et","lang_name":"Estonian"},{"language":"fi","lang_name":"Finnish"},{"language":"fr","lang_name":"French"},{"language":"de","lang_name":"German"},{"language":"el","lang_name":"Greek"},{"language":"hu","lang_name":"Hungarian"},{"language":"is","lang_name":"Icelandic"},{"language":"id","lang_name":"Indonesian"},{"language":"ky","lang_name":"Kirghiz"},{"language":"lv","lang_name":"Latvian"},{"language":"lt","lang_name":"Lithuanian"},{"language":"mg","lang_name":"Malagasy"},{"language":"pl","lang_name":"Polish"},{"language":"pt","lang_name":"Portuguese"},{"language":"ro","lang_name":"Romanian"},{"language":"es","lang_name":"Spanish"},{"language":"sv","lang_name":"Swedish"},{"language":"tl","lang_name":"Tagalog"},{"language":"tk","lang_name":"Turkmen"},{"language":"tvl","lang_name":"Tuvalu"}]},{"phelps":"BH11209","text":"## JAR EO EKADU\n\n*(SHORT OBLIGATORY PRAYER)\n\n* Jar kake juon allen ilo 24 awa otemjij, ilo raeleb\n\nIj kamol, O ao Anij, bwe Kwar kommane io bwe in jela kin Yuk im kabun nan Yuk. Ij kwalok, ilo ien in, ao mojno im Am kajur, ao jeramol im Am jeramon. Ejelok bar Anij Ijelokim, Eo ej jiban ilo ien uota, Eo ej mour kin E make.","name":"Short Obligatory Prayer","category":"JAR EO EKADU","cat_order":5,"order_in_cat":1,"source":"bahaiprayers.net","version":"4345ebc5-16ee-4526-9835-082dd8ce1810","translations":[{"language":"af","lang_name":"Afrikaans"},{"language":"sq","lang_name":"Albanian"},{"language":"am","lang_name":"Amharic"},{"language":"ar","lang_name":"Arabic"},{"language":"ar-translit","lang_name":"Arabic (Latin)"},{"language":"az","lang_name":"Azerbaijani"},{"language":"sne","lang_name":"Bau Bidayuh"},{"language":"be","lang_name":"Belarusian"},{"language":"bi","lang_name":"Bislama"},{"language":"bs","lang_name":"Bosnian"},{"language":"bg","lang_name":"Bulgarian"},{"language":"ca","lang_name":"Catalan"},{"language":"km","lang_name":"Central Khmer"},{"language":"ny","lang_name":"Chichewa"},{"language":"chn","lang_name":"Chinook Jargon"},{"language":"co","lang_name":"Corsican"},{"language":"cr","lang_name":"Cree"},{"language":"dgz","lang_name":"Daga"},{"language":"dak","lang_name":"Dakota"},{"language":"da","lang_name":"Danish"},{"language":"nl","lang_name":"Dutch"},{"language":"en","lang_name":"English"},{"language":"eo","lang_name":"Esperanto"},{"language":"fo","lang_name":"Faroese"},{"language":"fj","lang_name":"Fijian"},{"language":"fi","lang_name":"Finnish"},{"language":"fr","lang_name":"French"},{"language":"lg","lang_name":"Ganda"},{"language":"de","lang_name":"German"},{"language":"gil","lang_name":"Gilbertese"},{"language":"el","lang_name":"Greek"},{"language":"ht","lang_name":"Haitian Creole"},{"language":"hur","lang_name":"Halkomelem"},{"language":"ha","lang_name":"Hausa"},{"language":"haw","lang_name":"Hawaiian"},{"language":"hz","lang_name":"Herero"},{"language":"ho","lang_name":"Hiri Motu"},{"language":"hu","lang_name":"Hungarian"},{"language":"iba","lang_name":"Iban"},{"language":"is","lang_name":"Icelandic"},{"language":"id","lang_name":"Indonesian"},{"language":"ik","lang_name":"Inupiaq"},{"language":"it","lang_name":"Italian"},{"language":"ja","lang_name":"Japanese"},{"language":"kl","lang_name":"Kalaallisut"},{"language":"kn","lang_name":"Kannada"},{"language":"naq","lang_name":"Khoekhoegowab"},{"language":"kiw","lang_name":"Kiwai"},{"language":"ksd","lang_name":"Kuanua"},{"language":"dih","lang_name":"Kumiai"},{"language":"lkt","lang_name":"Lakota"},{"language":"lv","lang_name":"Latvian"},{"language":"lt","lang_name":"Lithuanian"},{"language":"lb","lang_name":"Luxembourgish"},{"language":"mg","lang_name":"Malagasy"},{"language":"ml","lang_name":"Malayalam"},{"language":"mt","lang_name":"Maltese"},{"language":"mi","lang_name":"Maori"},{"language":"med","lang_name":"Melpa"},{"language":"apm","lang_name":"Mescalero Apache"},{"language":"moh","lang_name":"Mohawk"},{"language":"meu","lang_name":"Motu"},{"language":"nal","lang_name":"Nalik"},{"language":"nv","lang_name":"Navajo"},{"language":"ne","lang_name":"Nepali"},{"language":"no","lang_name":"Norwegian"},{"language":"oj","lang_name":"Ojibwe"},{"language":"pap","lang_name":"Papiamento"},{"language":"fa","lang_name":"Persian"},{"language":"fa-translit","lang_name":"Persian (Latin)"},{"language":"pl","lang_name":"Polish"},{"language":"pt","lang_name":"Portuguese"},{"language":"pot","lang_name":"Potawatomi"},{"language":"ro","lang_name":"Romanian"},{"language":"diu","lang_name":"Rugciriku"},{"language":"ru","lang_name":"Russian"},{"language":"se","lang_name":"Sami"},{"language":"shs","lang_name":"Shuswap (Secwepemctsín)"},{"language":"sk","lang_name":"Slovak"},{"language":"es","lang_name":"Spanish"},{"language":"srn","lang_name":"Sranan Tongo"},{"language":"sw","lang_name":"Swahili"},{"language":"sv","lang_name":"Swedish"},{"language":"tl","lang_name":"Tagalog"},{"language":"ta","lang_name":"Tamil"},{"language":"te","lang_name":"Telugu"},{"language":"th","lang_name":"Thai"},{"language":"thp","lang_name":"Thompson"},{"language":"tpi","lang_name":"Tok Pisin"},{"language":"tvl","lang_name":"Tuvalu"},{"language":"ur","lang_name":"Urdu"},{"language":"cy","lang_name":"Welsh"},{"language":"fy","lang_name":"Western Frisian"}]},{"phelps":"BH08604","text":"O Kwe eo im Turin mejen ej unjen ao kabun, im aibuijuij eo An ej jikin ao kone, im ijo Jikin ej menin in ao kotobar. Nebar E ej ao kejatdrikdrik, wonake eo An ej karejera, im yokwe eo An ej unjen mour eo ao, ao kwalok kake E ej menin ao jokane, An ebake io ej konan eo ao, im an bed ibba ej konan im kotobar eo ao elab tata. Ij oware Yuk, bwe Kwon jab drebij jen io men ko im Kwar kalikari nan dri kelet ro Am ilubiljin ro dri jilkam. Letok nan io bareinwot men ko romman an lalin im lal eo ej itok. Kwe ilo mol Kwoj King in armij otemjij. Ebar ejelok Anij Ijelokim, Eo Dri jolok bwid indreo, Eo ejelok jonan An jouij.","category":"JAR IN JIBAN","cat_order":6,"order_in_cat":1,"source":"bahaiprayers.net","version":"0da219f8-53d6-4d8c-a64f-ffc36b1849d1","translations":[{"language":"af","lang_name":"Afrikaans"},{"language":"ar","lang_name":"Arabic"},{"language":"ar-translit","lang_name":"Arabic (Latin)"},{"language":"az","lang_name":"Azerbaijani"},{"language":"bn","lang_name":"Bengali"},{"language":"bs","lang_name":"Bosnian"},{"language":"bg","lang_name":"Bulgarian"},{"language":"ca","lang_name":"Catalan"},{"language":"nl","lang_name":"Dutch"},{"language":"en","lang_name":"English"},{"language":"fr","lang_name":"French"},{"language":"de","lang_name":"German"},{"language":"gil","lang_name":"Gilbertese"},{"language":"el","lang_name":"Greek"},{"language":"hu","lang_name":"Hungarian"},{"language":"is","lang_name":"Icelandic"},{"language":"id","lang_name":"Indonesian"},{"language":"lv","lang_name":"Latvian"},{"language":"ml","lang_name":"Malayalam"},{"language":"no","lang_name":"Norwegian"},{"language":"pl","lang_name":"Polish"},{"language":"pt","lang_name":"Portuguese"},{"language":"ro","lang_name":"Romanian"},{"language":"sm","lang_name":"Samoan"},{"language":"sk","lang_name":"Slovak"},{"language":"sl","lang_name":"Slovenian"},{"language":"es","lang_name":"Spanish"},{"language":"tl","lang_name":"Tagalog"},{"language":"tvl","lang_name":"Tuvalu"},{"language":"vi","lang_name":"Vietnamese"}]},{"phelps":"BH00868WIT","text":"Ao Anij, Eo ij kabun im kautiej E, ao King, Eo buruo eaikuiji ! Loo, ta emaron kwalok ainikien kamolol ko ao nan Yuk? Iar jerata im jol, Kwar karuj io, iar einwot juon eo emij, Kwar kemour io kin dren kwojarjar eo Am ejelok jemlokin im emoj an tor tok jen Naan in tiriamo eo Am elab.\n\nDri onake Eo ekwojarkar! Aolep menin komanman rar walok jen kejramon eo Am; jab drebij ir jen dren ko drenin jouij eo Am, ak jen lomoto in tiriamo eo Am. Ij badrikdrik im kajitok Ibbam nan jiban io ilo aolep ien im ilo aolep wewen ko, im bukot jen lan in tiriamo eo Am konan eo Am jen etto. Kwe ilo mol Iroij in jouij im Utiej tata an ailin in iroij eo ejelok jemlokin","category":"JAR IN JIBAN","cat_order":6,"order_in_cat":2,"source":"bahaiprayers.net","version":"a03e9f60-4bcc-471f-b18b-f102202b1986","translations":[{"language":"af","lang_name":"Afrikaans"},{"language":"am","lang_name":"Amharic"},{"language":"eu","lang_name":"Basque"},{"language":"bs","lang_name":"Bosnian"},{"language":"bg","lang_name":"Bulgarian"},{"language":"da","lang_name":"Danish"},{"language":"nl","lang_name":"Dutch"},{"language":"en","lang_name":"English"},{"language":"eo","lang_name":"Esperanto"},{"language":"et","lang_name":"Estonian"},{"language":"fr","lang_name":"French"},{"language":"de","lang_name":"German"},{"language":"el","lang_name":"Greek"},{"language":"ht","lang_name":"Haitian Creole"},{"language":"hu","lang_name":"Hungarian"},{"language":"it","lang_name":"Italian"},{"language":"lv","lang_name":"Latvian"},{"language":"no","lang_name":"Norwegian"},{"language":"pl","lang_name":"Polish"},{"language":"pt","lang_name":"Portuguese"},{"language":"ro","lang_name":"Romanian"},{"language":"es","lang_name":"Spanish"},{"language":"sv","lang_name":"Swedish"},{"language":"tl","lang_name":"Tagalog"}]},{"phelps":"BH02848","text":"O ao Anij im ao Master! Na ij dri jelkam im nejin dri jelkam. Emoj ao ruj tok jen ion kinio ilo jimarokin rainin einwot an Iju Ran in juon wot eo Am moj an romak tok jen jorantak in konan eo Am, im emoj an romak ion aolepen lal, ekkar nan ta eo emoj je im kakien kake ilo Buk ko Am.\n\nNebar Yuk, O ao Iroij, einwot am rujtok iumin meram in jelalokjen eo Am. Jilikinlaltak iom, bareinwot, O ao Anij, ta eo enaj kemaron kim bwe kemin ellok jen jabrewot ak Kwe wot, im jolok jabrewot men otmejij ijelokin wot Kwe. Kallikar nan io, bareinwot, im nan ro otemjij im rebake io, im ro nuku, man im kora jimor, kin men ko remmon ilo mour in im ilo mour eo tokelik. Kejbarok kim, bareinwot, kin kejbarok eo Am ejamin likjab, O Kwe eo Jitenburu an men in komanman otemjij im Konan eo an lan im lal, jen ro im Kwar kalikar ir bwe rej Dri Jerawiwi, im rej kabo armij otemjij. Kwokajur nan kommane ta eo Kwokonan. Emol, Kwe Dri Maron, Dri Jiban ilo ien uota, Eo Ej Bed kin E make.\n\nKejramon, O Iroij ao Anij, Eo im Kwar likit Ion aolepen Title ko Am remon tata, im ilo E Kwar kejbel emmon jen nana, im jiban kim bwe kemin kommane ta eo Kwokonan. Kejramon, bareinwot, O ao Anij, Ro im rej Naan im Leta ko Am, im ro im emoj air oktak im rewaj nan Yuk, im ronjake kir eo Am.\n\nEmol, Kwoj Iroij im King an armij otemjij, im maron ion aolep men otemjij.","category":"JAR IN JIBON","cat_order":7,"order_in_cat":1,"source":"bahaiprayers.net","version":"1b72b40d-3afd-4333-884f-3eec3dc4dc14","translations":[{"language":"af","lang_name":"Afrikaans"},{"language":"az","lang_name":"Azerbaijani"},{"language":"bi","lang_name":"Bislama"},{"language":"bg","lang_name":"Bulgarian"},{"language":"nl","lang_name":"Dutch"},{"language":"en","lang_name":"English"},{"language":"fi","lang_name":"Finnish"},{"language":"fr","lang_name":"French"},{"language":"de","lang_name":"German"},{"language":"gil","lang_name":"Gilbertese"},{"language":"el","lang_name":"Greek"},{"language":"ht","lang_name":"Haitian Creole"},{"language":"hu","lang_name":"Hungarian"},{"language":"id","lang_name":"Indonesian"},{"language":"lv","lang_name":"Latvian"},{"language":"lb","lang_name":"Luxembourgish"},{"language":"ms","lang_name":"Malay"},{"language":"mr","lang_name":"Marathi"},{"language":"no","lang_name":"Norwegian"},{"language":"pl","lang_name":"Polish"},{"language":"pt","lang_name":"Portuguese"},{"language":"ro","lang_name":"Romanian"},{"language":"ru","lang_name":"Russian"},{"language":"sk","lang_name":"Slovak"},{"language":"st","lang_name":"Southern Sotho"},{"language":"tl","lang_name":"Tagalog"},{"language":"uk","lang_name":"Ukrainian"},{"language":"ur","lang_name":"Urdu"},{"language":"vi","lang_name":"Vietnamese"}]},{"phelps":"BH00009GRA","text":"Ekijkan ao maron kiki, O Anij, ao Anij, elane mej ko mejen ro rej on kake Yuk rej ruj wot kin air bed etto lok jen Kwe; im ekijkan ao maron Bábu im kakije ak jitob an ro rej yokwe Yuk reburomij ilo air bed ettolok jen Turum?\n\nEmoj ao ajewaj, O ao Iroij, jitob eo ao im aolepa nan tu-anbijmaron in maron im kejbarok eo Am, im ij Bábu ion bito kin kajur eo Am, im jerkak lontak ekkar nan Ankilam im Am konan. Kwe, ilo mol, Dri kejbarok, Dri wonake, Eo ekajur potata, Eo ejelok jonan an kajur.\n\nKin kajur eo Am! Ejelok bar juon men inaj, ilo ien ao kiki ak ilo ien ao ruj, ak men eo wot kwoj konan. Na ij Am dri jerbal im ij likit io ilubdren Beim. Kwon jouij im jiban io bwe in maron kadriwoj lok melu in monono in jouij eo Am. Enin, ilo mol, ej kejatdrikdrik eo ao im an ro jet im rej monono ilo air bed ebake Yuk. Neber Yuk, O Iroij in lal otemjelok!","category":"JAR IN JOTA","cat_order":8,"order_in_cat":1,"source":"bahaiprayers.net","version":"89866cd2-ca63-4db1-a0d5-362051d4aa40","translations":[{"language":"af","lang_name":"Afrikaans"},{"language":"az","lang_name":"Azerbaijani"},{"language":"bn","lang_name":"Bengali"},{"language":"bi","lang_name":"Bislama"},{"language":"bs","lang_name":"Bosnian"},{"language":"bg","lang_name":"Bulgarian"},{"language":"ca","lang_name":"Catalan"},{"language":"ch","lang_name":"Chamorro"},{"language":"ny","lang_name":"Chichewa"},{"language":"da","lang_name":"Danish"},{"language":"nl","lang_name":"Dutch"},{"language":"en","lang_name":"English"},{"language":"eo","lang_name":"Esperanto"},{"language":"et","lang_name":"Estonian"},{"language":"fi","lang_name":"Finnish"},{"language":"fr","lang_name":"French"},{"language":"lg","lang_name":"Ganda"},{"language":"de","lang_name":"German"},{"language":"el","lang_name":"Greek"},{"language":"ht","lang_name":"Haitian Creole"},{"language":"haw","lang_name":"Hawaiian"},{"language":"hz","lang_name":"Herero"},{"language":"hu","lang_name":"Hungarian"},{"language":"is","lang_name":"Icelandic"},{"language":"id","lang_name":"Indonesian"},{"language":"it","lang_name":"Italian"},{"language":"kl","lang_name":"Kalaallisut"},{"language":"lv","lang_name":"Latvian"},{"language":"lb","lang_name":"Luxembourgish"},{"language":"mg","lang_name":"Malagasy"},{"language":"ms","lang_name":"Malay"},{"language":"ml","lang_name":"Malayalam"},{"language":"mt","lang_name":"Maltese"},{"language":"mn","lang_name":"Mongolian"},{"language":"ne","lang_name":"Nepali"},{"language":"no","lang_name":"Norwegian"},{"language":"pap","lang_name":"Papiamento"},{"language":"pl","lang_name":"Polish"},{"language":"pt","lang_name":"Portuguese"},{"language":"ro","lang_name":"Romanian"},{"language":"sk","lang_name":"Slovak"},{"language":"sl","lang_name":"Slovenian"},{"language":"st","lang_name":"Southern Sotho"},{"language":"es","lang_name":"Spanish"},{"language":"srn","lang_name":"Sranan Tongo"},{"language":"sw","lang_name":"Swahili"},{"language":"sv","lang_name":"Swedish"},{"language":"tl","lang_name":"Tagalog"},{"language":"zh-Hant","lang_name":"Traditional Chinese"},{"language":"uk","lang_name":"Ukrainian"},{"language":"ur","lang_name":"Urdu"},{"language":"cy","lang_name":"Welsh"}]},{"phelps":"AB11605","text":"Et eo Etam ej menin kemour io, O ao Anij, im ao kemejmej Yuk ej menin kejmour io, ebake Yuk ej ao kejatdrikdrik, im yokwe eo ao nan Yuk ej motta. Tiriamo eo Am nan io ej menin kemour im kejmour io ilo lalin im ilo lal eo ej itok. Kwe, ilo mol, Kwobrak kin menin jeramon, Eo ejelalokjen, Eo Dri meletlet otem meletlet.","category":"JAR IN KEMOUR","cat_order":9,"order_in_cat":1,"source":"bahaiprayers.net","version":"066808f7-6358-4b58-ac52-26bdeb6c893f","translations":[{"language":"az","lang_name":"Azerbaijani"},{"language":"eu","lang_name":"Basque"},{"language":"bs","lang_name":"Bosnian"},{"language":"bg","lang_name":"Bulgarian"},{"language":"ca","lang_name":"Catalan"},{"language":"nl","lang_name":"Dutch"},{"language":"en","lang_name":"English"},{"language":"et","lang_name":"Estonian"},{"language":"fr","lang_name":"French"},{"language":"de","lang_name":"German"},{"language":"el","lang_name":"Greek"},{"language":"ht","lang_name":"Haitian Creole"},{"language":"ha","lang_name":"Hausa"},{"language":"hu","lang_name":"Hungarian"},{"language":"is","lang_name":"Icelandic"},{"language":"id","lang_name":"Indonesian"},{"language":"mn","lang_name":"Mongolian"},{"language":"no","lang_name":"Norwegian"},{"language":"fa","lang_name":"Persian"},{"language":"fa-translit","lang_name":"Persian (Latin)"},{"language":"pl","lang_name":"Polish"},{"language":"pt","lang_name":"Portuguese"},{"language":"ro","lang_name":"Romanian"},{"language":"ru","lang_name":"Russian"},{"language":"zh-Hans","lang_name":"Simplified Chinese"},{"language":"sk","lang_name":"Slovak"},{"language":"es","lang_name":"Spanish"},{"language":"tl","lang_name":"Tagalog"},{"language":"uk","lang_name":"Ukrainian"},{"language":"vi","lang_name":"Vietnamese"}]},{"phelps":"BH10505","text":"O ao Anij! O ao Anij! Emol, dri jerbal rein Am rej oktak waj nan Kwe, bukot jiban jen ailin in tiriamo eo Am. Emol, Am kwojarjar emoj an kinor waj ir im emoj air urur kin kijeek in yokwe eo Am, bukot kejramon jen ailin eo Am ekabwilonlon, ilo air kejetdrikdrik bwe renaj bed ilo ailin eo Am ilan. Emol, elab air kijoror in bok kejramon eo ej itok jen Kwe, ilo air konan bok meran jen al in mol. O Iroij! Komman bwe ren lamp ko reromak, kokkale ko kokkalen tiriamo, wijki ko eobrak leier im iju ko reromak. Komman bwe ren jutaklontak im bok kunaier ilo jerbal eo Am im koba waj Ibbam ilo korak in yokwe eo Am, ilo air kijoror in bok meram in kejramon eo Am. O Iroij! Komman bwe ren kokkalen tel, flag ko an ailin eo Am ejelok jemlokin, no ko noon lomalo in tiriamo eo Am, glass ko glass in meram in utiej potata eo Am.\n\nEmol, Kwe Dri jouij. Emol, Kwe Dri tiriamo. Emol, Kwoaurok, Eo Jitenburu.","category":"JAR IN KWELOK KO","cat_order":10,"order_in_cat":1,"source":"bahaiprayers.net","version":"ce6e208c-a183-43f3-974a-e3349fe96bfc","translations":[{"language":"af","lang_name":"Afrikaans"},{"language":"sq","lang_name":"Albanian"},{"language":"hy","lang_name":"Armenian"},{"language":"sne","lang_name":"Bau Bidayuh"},{"language":"bn","lang_name":"Bengali"},{"language":"bs","lang_name":"Bosnian"},{"language":"ch","lang_name":"Chamorro"},{"language":"chr","lang_name":"Cherokee"},{"language":"ny","lang_name":"Chichewa"},{"language":"chn","lang_name":"Chinook Jargon"},{"language":"co","lang_name":"Corsican"},{"language":"hr","lang_name":"Croatian"},{"language":"cs","lang_name":"Czech"},{"language":"dgz","lang_name":"Daga"},{"language":"dak","lang_name":"Dakota"},{"language":"da","lang_name":"Danish"},{"language":"nl","lang_name":"Dutch"},{"language":"en","lang_name":"English"},{"language":"eo","lang_name":"Esperanto"},{"language":"et","lang_name":"Estonian"},{"language":"fo","lang_name":"Faroese"},{"language":"fj","lang_name":"Fijian"},{"language":"fr","lang_name":"French"},{"language":"lg","lang_name":"Ganda"},{"language":"el","lang_name":"Greek"},{"language":"gu","lang_name":"Gujarati"},{"language":"ht","lang_name":"Haitian Creole"},{"language":"hur","lang_name":"Halkomelem"},{"language":"hz","lang_name":"Herero"},{"language":"hi","lang_name":"Hindi"},{"language":"is","lang_name":"Icelandic"},{"language":"id","lang_name":"Indonesian"},{"language":"ik","lang_name":"Inupiaq"},{"language":"it","lang_name":"Italian"},{"language":"ja","lang_name":"Japanese"},{"language":"kl","lang_name":"Kalaallisut"},{"language":"kn","lang_name":"Kannada"},{"language":"naq","lang_name":"Khoekhoegowab"},{"language":"ko","lang_name":"Korean"},{"language":"ksd","lang_name":"Kuanua"},{"language":"dih","lang_name":"Kumiai"},{"language":"lkt","lang_name":"Lakota"},{"language":"lv","lang_name":"Latvian"},{"language":"lb","lang_name":"Luxembourgish"},{"language":"ms","lang_name":"Malay"},{"language":"ml","lang_name":"Malayalam"},{"language":"mt","lang_name":"Maltese"},{"language":"mi","lang_name":"Maori"},{"language":"med","lang_name":"Melpa"},{"language":"mic","lang_name":"Mikmaq"},{"language":"mn","lang_name":"Mongolian"},{"language":"meu","lang_name":"Motu"},{"language":"nal","lang_name":"Nalik"},{"language":"nv","lang_name":"Navajo"},{"language":"ne","lang_name":"Nepali"},{"language":"no","lang_name":"Norwegian"},{"language":"pap","lang_name":"Papiamento"},{"language":"pl","lang_name":"Polish"},{"language":"pt","lang_name":"Portuguese"},{"language":"ro","lang_name":"Romanian"},{"language":"diu","lang_name":"Rugciriku"},{"language":"sm","lang_name":"Samoan"},{"language":"sr","lang_name":"Serbian"},{"language":"shh","lang_name":"Shoshoni"},{"language":"zh-Hans","lang_name":"Simplified Chinese"},{"language":"sk","lang_name":"Slovak"},{"language":"sl","lang_name":"Slovenian"},{"language":"srn","lang_name":"Sranan Tongo"},{"language":"sw","lang_name":"Swahili"},{"language":"sv","lang_name":"Swedish"},{"language":"tl","lang_name":"Tagalog"},{"language":"ta","lang_name":"Tamil"},{"language":"te","lang_name":"Telugu"},{"language":"th","lang_name":"Thai"},{"language":"tpi","lang_name":"Tok Pisin"},{"language":"zh-Hant","lang_name":"Traditional Chinese"},{"language":"tk","lang_name":"Turkmen"},{"language":"tvl","lang_name":"Tuvalu"},{"language":"uk","lang_name":"Ukrainian"},{"language":"ur","lang_name":"Urdu"},{"language":"vi","lang_name":"Vietnamese"},{"language":"cy","lang_name":"Welsh"},{"language":"fy","lang_name":"Western Frisian"}]},{"phelps":"BB00623","text":"Ewor ke bar juon Dri jolok aban ko ijelokin Anij? Jen ba: Nebar Anij! E Ej Anij! Aolep rej Dri jelkan, im aolep rej bed kin Kilan!","category":"JIBAN KIN MENIN MELEJON KO","cat_order":11,"order_in_cat":1,"source":"bahaiprayers.net","version":"a84409db-0e37-4136-892c-d4cebf1fc4be","translations":[{"language":"sq","lang_name":"Albanian"},{"language":"ar","lang_name":"Arabic"},{"language":"ar-translit","lang_name":"Arabic (Latin)"},{"language":"hy","lang_name":"Armenian"},{"language":"az","lang_name":"Azerbaijani"},{"language":"eu","lang_name":"Basque"},{"language":"sne","lang_name":"Bau Bidayuh"},{"language":"be","lang_name":"Belarusian"},{"language":"bn","lang_name":"Bengali"},{"language":"bla","lang_name":"Blackfoot"},{"language":"bs","lang_name":"Bosnian"},{"language":"bg","lang_name":"Bulgarian"},{"language":"ca","lang_name":"Catalan"},{"language":"km","lang_name":"Central Khmer"},{"language":"ch","lang_name":"Chamorro"},{"language":"ny","lang_name":"Chichewa"},{"language":"chn","lang_name":"Chinook Jargon"},{"language":"co","lang_name":"Corsican"},{"language":"hr","lang_name":"Croatian"},{"language":"cs","lang_name":"Czech"},{"language":"dgz","lang_name":"Daga"},{"language":"da","lang_name":"Danish"},{"language":"en","lang_name":"English"},{"language":"fo","lang_name":"Faroese"},{"language":"fj","lang_name":"Fijian"},{"language":"fi","lang_name":"Finnish"},{"language":"fr","lang_name":"French"},{"language":"de","lang_name":"German"},{"language":"gil","lang_name":"Gilbertese"},{"language":"gux","lang_name":"Gourmanchéma"},{"language":"el","lang_name":"Greek"},{"language":"gu","lang_name":"Gujarati"},{"language":"ha","lang_name":"Hausa"},{"language":"haw","lang_name":"Hawaiian"},{"language":"hz","lang_name":"Herero"},{"language":"hi","lang_name":"Hindi"},{"language":"ho","lang_name":"Hiri Motu"},{"language":"hu","lang_name":"Hungarian"},{"language":"iba","lang_name":"Iban"},{"language":"is","lang_name":"Icelandic"},{"language":"id","lang_name":"Indonesian"},{"language":"ik","lang_name":"Inupiaq"},{"language":"ga","lang_name":"Irish"},{"language":"it","lang_name":"Italian"},{"language":"ja","lang_name":"Japanese"},{"language":"kl","lang_name":"Kalaallisut"},{"language":"kn","lang_name":"Kannada"},{"language":"ky","lang_name":"Kirghiz"},{"language":"kiw","lang_name":"Kiwai"},{"language":"ko","lang_name":"Korean"},{"language":"ksd","lang_name":"Kuanua"},{"language":"kgf","lang_name":"Kube"},{"language":"dih","lang_name":"Kumiai"},{"language":"lkt","lang_name":"Lakota"},{"language":"lo","lang_name":"Lao"},{"language":"lv","lang_name":"Latvian"},{"language":"lb","lang_name":"Luxembourgish"},{"language":"mg","lang_name":"Malagasy"},{"language":"ms","lang_name":"Malay"},{"language":"ml","lang_name":"Malayalam"},{"language":"mi","lang_name":"Maori"},{"language":"mr","lang_name":"Marathi"},{"language":"moh","lang_name":"Mohawk"},{"language":"mn","lang_name":"Mongolian"},{"language":"cnr","lang_name":"Montenegrin"},{"language":"meu","lang_name":"Motu"},{"language":"nal","lang_name":"Nalik"},{"language":"nv","lang_name":"Navajo"},{"language":"ne","lang_name":"Nepali"},{"language":"no","lang_name":"Norwegian"},{"language":"one","lang_name":"Oneida"},{"language":"pap","lang_name":"Papiamento"},{"language":"pl","lang_name":"Polish"},{"language":"pt","lang_name":"Portuguese"},{"language":"ro","lang_name":"Romanian"},{"language":"diu","lang_name":"Rugciriku"},{"language":"ru","lang_name":"Russian"},{"language":"se","lang_name":"Sami"},{"language":"sm","lang_name":"Samoan"},{"language":"zh-Hans","lang_name":"Simplified Chinese"},{"language":"sk","lang_name":"Slovak"},{"language":"sl","lang_name":"Slovenian"},{"language":"st","lang_name":"Southern Sotho"},{"language":"es","lang_name":"Spanish"},{"language":"srn","lang_name":"Sranan Tongo"},{"language":"sw","lang_name":"Swahili"},{"language":"sv","lang_name":"Swedish"},{"language":"tl","lang_name":"Tagalog"},{"language":"ta","lang_name":"Tamil"},{"language":"th","lang_name":"Thai"},{"language":"tpi","lang_name":"Tok Pisin"},{"language":"tk","lang_name":"Turkmen"},{"language":"tvl","lang_name":"Tuvalu"},{"language":"uk","lang_name":"Ukrainian"},{"language":"wam","lang_name":"Wampanoag"},{"language":"cy","lang_name":"Welsh"},{"language":"fy","lang_name":"Western Frisian"}]},{"phelps":"BB00630","text":"O Iroij! Kwoj Dri jolok aolep menin buromoj, im Dri namejlan aolep menin aban. Kwe Eo Kwoj Dri jolok buromoj im kanemkwoj ro dri kamokoko, im Dri lomor an aolep armij. O Iroij! Letok anemkwoj kin tiriamo eo Am, im bwine io ilubljin dri jerbal ro Am im emoj air bok lomor.","category":"JIBAN KIN MENIN MELEJON KO","cat_order":11,"order_in_cat":2,"source":"bahaiprayers.net","version":"94633f28-3e51-4514-85ec-eabc85e60c96","translations":[{"language":"sq","lang_name":"Albanian"},{"language":"hy","lang_name":"Armenian"},{"language":"az","lang_name":"Azerbaijani"},{"language":"sne","lang_name":"Bau Bidayuh"},{"language":"bg","lang_name":"Bulgarian"},{"language":"ca","lang_name":"Catalan"},{"language":"ceb","lang_name":"Cebuano"},{"language":"da","lang_name":"Danish"},{"language":"nl","lang_name":"Dutch"},{"language":"en","lang_name":"English"},{"language":"eo","lang_name":"Esperanto"},{"language":"et","lang_name":"Estonian"},{"language":"fi","lang_name":"Finnish"},{"language":"fr","lang_name":"French"},{"language":"lg","lang_name":"Ganda"},{"language":"de","lang_name":"German"},{"language":"el","lang_name":"Greek"},{"language":"ht","lang_name":"Haitian Creole"},{"language":"hi","lang_name":"Hindi"},{"language":"hu","lang_name":"Hungarian"},{"language":"is","lang_name":"Icelandic"},{"language":"id","lang_name":"Indonesian"},{"language":"ja","lang_name":"Japanese"},{"language":"kl","lang_name":"Kalaallisut"},{"language":"kn","lang_name":"Kannada"},{"language":"ko","lang_name":"Korean"},{"language":"lb","lang_name":"Luxembourgish"},{"language":"ms","lang_name":"Malay"},{"language":"ml","lang_name":"Malayalam"},{"language":"mt","lang_name":"Maltese"},{"language":"mn","lang_name":"Mongolian"},{"language":"ne","lang_name":"Nepali"},{"language":"pl","lang_name":"Polish"},{"language":"pt","lang_name":"Portuguese"},{"language":"ro","lang_name":"Romanian"},{"language":"ru","lang_name":"Russian"},{"language":"sr","lang_name":"Serbian"},{"language":"sk","lang_name":"Slovak"},{"language":"sl","lang_name":"Slovenian"},{"language":"es","lang_name":"Spanish"},{"language":"tl","lang_name":"Tagalog"},{"language":"te","lang_name":"Telugu"},{"language":"tet","lang_name":"Tetum"},{"language":"zh-Hant","lang_name":"Traditional Chinese"},{"language":"tvl","lang_name":"Tuvalu"},{"language":"uk","lang_name":"Ukrainian"}]},{"phelps":"AB07158","text":"Kwoaibuijuij, O ao Anij! Emol, dri jerbal rein Am rej kobatok iumin ailurlur in tiriamo eo Am im rej kobatok kin jouij im tiriamo eo Am. O Iroij! Jiban ilo lal in Am im ailin eo Am im lelok nan ir men ko remmon jen jouij im yokwe eo Am. O Iroij! kabin ir ilo air jerbal nan Yuk im jiban ir ilo air jerbal nan Yuk. Komman bwe ren kokkale ko kokkalen Et eo Etam ilo lal eo Am im kejbarok ir kin kejramon ko Am rejamin jemlok ilo lalin im ilo lal eo ej itok . O Iroij! Rej oware ailin in tiriamo eo Am im kajitok jiban jen jikin eo Am ej make wot. Emol, rej mare ekkar nan kakien eo Am. Kommane bwe ren kokkale ko kokkalen ainemon im mour in ibbben dron nan jemlokin mour. Emol, Kwokajur Potata, Kwomonmon, im Dri maron potata!","category":"MARE","cat_order":12,"order_in_cat":1,"source":"bahaiprayers.net","version":"9dad69c0-22f4-48ce-b517-e55d87ca0dc4","translations":[{"language":"sq","lang_name":"Albanian"},{"language":"hy","lang_name":"Armenian"},{"language":"sne","lang_name":"Bau Bidayuh"},{"language":"bs","lang_name":"Bosnian"},{"language":"ca","lang_name":"Catalan"},{"language":"ch","lang_name":"Chamorro"},{"language":"hr","lang_name":"Croatian"},{"language":"nl","lang_name":"Dutch"},{"language":"en","lang_name":"English"},{"language":"eo","lang_name":"Esperanto"},{"language":"et","lang_name":"Estonian"},{"language":"fo","lang_name":"Faroese"},{"language":"fr","lang_name":"French"},{"language":"de","lang_name":"German"},{"language":"gil","lang_name":"Gilbertese"},{"language":"el","lang_name":"Greek"},{"language":"ha","lang_name":"Hausa"},{"language":"hi","lang_name":"Hindi"},{"language":"hu","lang_name":"Hungarian"},{"language":"iba","lang_name":"Iban"},{"language":"is","lang_name":"Icelandic"},{"language":"id","lang_name":"Indonesian"},{"language":"it","lang_name":"Italian"},{"language":"naq","lang_name":"Khoekhoegowab"},{"language":"ky","lang_name":"Kirghiz"},{"language":"ksd","lang_name":"Kuanua"},{"language":"kgf","lang_name":"Kube"},{"language":"lv","lang_name":"Latvian"},{"language":"lb","lang_name":"Luxembourgish"},{"language":"ms","lang_name":"Malay"},{"language":"ml","lang_name":"Malayalam"},{"language":"mr","lang_name":"Marathi"},{"language":"med","lang_name":"Melpa"},{"language":"mn","lang_name":"Mongolian"},{"language":"ne","lang_name":"Nepali"},{"language":"no","lang_name":"Norwegian"},{"language":"pl","lang_name":"Polish"},{"language":"pt","lang_name":"Portuguese"},{"language":"ro","lang_name":"Romanian"},{"language":"sm","lang_name":"Samoan"},{"language":"sk","lang_name":"Slovak"},{"language":"es","lang_name":"Spanish"},{"language":"sw","lang_name":"Swahili"},{"language":"sv","lang_name":"Swedish"},{"language":"tl","lang_name":"Tagalog"},{"language":"ta","lang_name":"Tamil"},{"language":"tet","lang_name":"Tetum"},{"language":"tpi","lang_name":"Tok Pisin"},{"language":"zh-Hant","lang_name":"Traditional Chinese"},{"language":"tvl","lang_name":"Tuvalu"},{"language":"uk","lang_name":"Ukrainian"},{"language":"vi","lang_name":"Vietnamese"},{"language":"fy","lang_name":"Western Frisian"}]},{"phelps":"AB11094","text":"O ao Anij! O Kwe Ri-jolok bwid ko, ri-letok menin lelok ko, ri-jolok aban ko!\n\nIj akwelapIbam kin eo emoj an jolok nuknuk eo an kaniek im botoktok im wonlonwaj non lal eo an jitob.\n\nO ao Iroj! Kareoik ir jen bwid ko air, jolok burumij ko air im ukot ir jen bed ilo marok non meram. Koman bwe ren drelok jikin kalib in monono eo am, kareoik ir kin den eo ereo im ereo, koman bwe ren maron in lo romak ko Am ion tol eo eutiej tata.","category":"RO DRI MIJ","cat_order":13,"order_in_cat":1,"source":"bahaiprayers.net","version":"8d221400-3fd5-44fc-9b02-53d1a64a65e7","translations":[{"language":"af","lang_name":"Afrikaans"},{"language":"sq","lang_name":"Albanian"},{"language":"az","lang_name":"Azerbaijani"},{"language":"eu","lang_name":"Basque"},{"language":"bn","lang_name":"Bengali"},{"language":"bi","lang_name":"Bislama"},{"language":"bs","lang_name":"Bosnian"},{"language":"bg","lang_name":"Bulgarian"},{"language":"ca","lang_name":"Catalan"},{"language":"ch","lang_name":"Chamorro"},{"language":"hr","lang_name":"Croatian"},{"language":"da","lang_name":"Danish"},{"language":"nl","lang_name":"Dutch"},{"language":"en","lang_name":"English"},{"language":"eo","lang_name":"Esperanto"},{"language":"et","lang_name":"Estonian"},{"language":"fi","lang_name":"Finnish"},{"language":"fr","lang_name":"French"},{"language":"lg","lang_name":"Ganda"},{"language":"de","lang_name":"German"},{"language":"gil","lang_name":"Gilbertese"},{"language":"gux","lang_name":"Gourmanchéma"},{"language":"el","lang_name":"Greek"},{"language":"hz","lang_name":"Herero"},{"language":"hu","lang_name":"Hungarian"},{"language":"is","lang_name":"Icelandic"},{"language":"id","lang_name":"Indonesian"},{"language":"ik","lang_name":"Inupiaq"},{"language":"it","lang_name":"Italian"},{"language":"ja","lang_name":"Japanese"},{"language":"kl","lang_name":"Kalaallisut"},{"language":"kn","lang_name":"Kannada"},{"language":"naq","lang_name":"Khoekhoegowab"},{"language":"ky","lang_name":"Kirghiz"},{"language":"ko","lang_name":"Korean"},{"language":"kgf","lang_name":"Kube"},{"language":"lv","lang_name":"Latvian"},{"language":"mg","lang_name":"Malagasy"},{"language":"ml","lang_name":"Malayalam"},{"language":"mt","lang_name":"Maltese"},{"language":"mr","lang_name":"Marathi"},{"language":"ne","lang_name":"Nepali"},{"language":"no","lang_name":"Norwegian"},{"language":"kj","lang_name":"Oshikwanyama"},{"language":"pl","lang_name":"Polish"},{"language":"pt","lang_name":"Portuguese"},{"language":"ro","lang_name":"Romanian"},{"language":"diu","lang_name":"Rugciriku"},{"language":"se","lang_name":"Sami"},{"language":"sk","lang_name":"Slovak"},{"language":"sl","lang_name":"Slovenian"},{"language":"st","lang_name":"Southern Sotho"},{"language":"es","lang_name":"Spanish"},{"language":"srn","lang_name":"Sranan Tongo"},{"language":"sv","lang_name":"Swedish"},{"language":"tl","lang_name":"Tagalog"},{"language":"ta","lang_name":"Tamil"},{"language":"te","lang_name":"Telugu"},{"language":"tet","lang_name":"Tetum"},{"language":"ur","lang_name":"Urdu"},{"language":"cy","lang_name":"Welsh"},{"language":"fy","lang_name":"Western Frisian"}]}]
