{"pin":"AB02860","subcodes":[{"code":"AB02860","anchor":"","first_line":"O my God, my God! Muhammad hath hastened unto the sanctified court of Thy holiness and the precincts of Thy mercy, that he may attain unto Thy presence and behold [3.5s]","first_line_orig":"الهی الهی ان محمدا سرع الی ساحه قدسک و رحاب رحمانیتک حتی یدرک لقائک و ینظر  ","language":"5","word_count":"220","subjects":"@prayer for specific individuals; groups, @spiritual transformation, @primordial Covenant; the day of alast","translations":[]}]}
