{"pin":"AB02835","subcodes":[{"code":"AB02835","anchor":"","first_line":"O thou whom God hath reserved for the service of His Cause! Thy page hath been unfolded, observed and regarded, and from the reality of events [3.5s]","first_line_orig":"یا من ادخره الله لخدمه امره صفحه منشور منظور و ملحوظ گشت و بر حقیقت وقایع از  ","language":"3","word_count":"230","subjects":"@spiritual meetings; gatherings; devotional gatherings; feasts, @defending the Faith; protecting the Cause; apologetics, @teaching the Cause; call to teach, @divine grace, bounty, confirmations; spiritual capacity","translations":[]}]}
