{"pin":"AB02022","subcodes":[{"code":"AB02022","anchor":"","first_line":"O my God, my Lord! Thou beholdest souls attracted by the fragrances of the gardens of Thy sanctified Kingdom and gladdened by the verses [3.5s]","first_line_orig":"اللهم یا الهی تری نفوسا منجذبه بنفحات حدائق ملکوت تقدیسک و منشرحه بایات  ","language":"1","word_count":"270","subjects":"@martyrs and martyrdom, @spiritual transformation, @expressions of grief; lamentation; sadness, @chastisement and requital, @love of God","translations":[]}]}
