{"pin":"AB03854","subcodes":[{"code":"AB03854","anchor":"","first_line":"God, glorified and exalted be He, hath declared in His Mighty Book: \"On the Day when mankind shall arise before the Lord of the worlds.\" Know thou, O wayfarer [3.5s]","first_line_orig":"قال الله سبحانه و تعالی فی کتابه الحکیم یوم یقوم الناس لرب العالمین اعلم یا ایها السالک  ","language":"1","word_count":"190","subjects":"@Manifestation of God as sun, @differences between the Manifestations; station of distinction","translations":[]}]}
