{"pin":"AB03363","subcodes":[{"code":"AB03363","anchor":"","first_line":"O ancient servant of the Most Glorious Beauty! Praise be to God that in Adhirbayjan thou didst kindle a fire in the hearts of the heedless ones, and in that [3.5s]","first_line_orig":"ای بنده دیرین جمال ابهی الحمد لله در آذربایجان آذری بجان غافلان زدی و در آن  ","language":"5","word_count":"200","subjects":"@teaching the Cause; call to teach, @praise and encouragement, @trust and reliance in God; turning to Him at all times, @divine grace, bounty, confirmations; spiritual capacity, @the divine emanation; the all-pervading bounty of God","translations":[]}]}
