{"pin":"AB03803","subcodes":[{"code":"AB03803","anchor":"","first_line":"O ye friends of God and handmaidens of the All-Merciful! Render thanks unto God that ye have entered beneath the canopy of the loving-kindness of the Lord of all desire [3.5s]","first_line_orig":"ای یاران الهی و اماء رحمن شکر کنید خدا را که در ظل عنایت حضرت مقصود در آمدید  ","language":"5","word_count":"190","subjects":"@prayer for firmness in the Covenant, @thankfulness; gratitude, @steadfastness; perseverance; faithfulness","translations":[]}]}
