{"pin":"AB04480","subcodes":[{"code":"AB04480","anchor":"","first_line":"O thou awakened and vigilant one! It was the angel's melody that brought thee to consciousness, and the call reached thine ear. The deaf ear shall surely hear the call [3.5s]","first_line_orig":"ای هوشیار بیدار سروش یار بود که بهوش آمدی و ندا بگوش رسید سمع اصم البته ندای  ","language":"3","word_count":"170","subjects":"@power; greatness; centrality of the Covenant, @mysteries and their discovery; the mystical vision, @development of capacity and readiness, @spiritual transformation","translations":[]}]}
