{"pin":"AB04116","subcodes":[{"code":"AB04116","anchor":"","first_line":"O companion of 'Abdu'l-Bahá! Thy two letters arrived at the most propitious hour, and their perusal brought joy and spiritual delight [3.5s]","first_line_orig":"ای یار عبدالبهاء دو طغرا نامه شما در بهترین ساعت وارد و از قرائتش روح و ریحان  ","language":"3","word_count":"180","subjects":"@praise and encouragement, @divine grace, bounty, confirmations; spiritual capacity, @business; financial; property matters, @service to others; to the Cause of God","translations":[]}]}
