{"pin":"AB06426","subcodes":[{"code":"AB06426","anchor":"","first_line":"O thou who art preparing to receive knowledge from the Herald of the Kingdom! I have read thy letter in which thou showed thy desire","first_line_orig":"ایتها المتهیئه للتعلم من منادی الملکوت قد تلوت رقیمتک التی اظهرت بها رغبتک  ","language":"1","word_count":"130","subjects":"@spiritual emotions and susceptibilities, @divine grace, bounty, confirmations; spiritual capacity, @the power of words; of speech, @firmness in the Covenant, @the Word of God; influence and centrality of, @angels","translations":[]}]}
