{"pin":"AB11056","subcodes":[{"code":"AB11056","anchor":"","title":"The Meaning of the \"Mysteries\"","first_line":"By “mysteries” is meant such matters and questions as are remote and hidden from the minds","first_line_orig":"مقصد از سر مطالب و مسائلی که از عقول و ادراک خلق دور و مستور بعد چون شخص کاملی  ","language":"3","word_count":"50","subjects":"@mysteries and their discovery; the mystical vision, @prophecy and fulfillment, @the truth of past religions and sacred scriptures","translations":[]}]}
