{"pin":"AB11651","subcodes":[{"code":"AB11651","anchor":"","first_line":"O merciful friends, O friends of the Most Glorious Beauty, O companions of Abdu'l-Baha, O those firm in the Covenant and Testament [3.5s]","first_line_orig":"ای احبای رحمانی ای دوستان جمال ابهی ای یاران عبدالبهاء ای ثابتان بر عهد و پیمان  ","language":"3","word_count":"340","subjects":"@sacrifice of self; mystery of sacrifice, @walking the spiritual path; spiritual wayfaring; the virtuous life, @praise and encouragement, @characteristics and conduct of true believers, @wisdom [hikmat]","translations":[]}]}
