{"pin":"ABU0664","subcodes":[{"code":"ABU0664","anchor":"","title":"Words spoken in 1916 in Haifa","first_line":"In Switzerland did we traverse the path toward the hotel that had been erected upon the mountain, when suddenly I beheld a strange figure wearing a European hat [3.5s]","first_line_orig":"در سویس راه میرفتیم بسمت هتلی که بالای کوه ساخته‌اند یکدفعه نگاه کردم دیدم هیکل غریبی با کلاه فرنگی  ","language":"3","word_count":"440","subjects":"@predictions and prophecies, @impossibility of true worship of God","translations":[]}]}
