{"pin":"ABU1004","subcodes":[{"code":"ABU1004","anchor":"","title":"Words spoken at Haifa Pilgrim House, 1920-11-16","first_line":"The Baha'is should sacrifice life in the path of each other... It must be so that each one of the friends should prefer others to himself.","word_count":"310","subjects":"@present and future calamities; war; universal convulsion, @forces of light and darkness; integration and disintegration, @the golden rule; regard for one's neighbor; doing unto others, @sacrifice of self; mystery of sacrifice, @martyrs and martyrdom, @growth of the Cause, @predictions and prophecies","translations":[]}]}
