{"pin":"ABU2229","subcodes":[{"code":"ABU2229","anchor":"","title":"Words spoken on 1912-12-24 in London","first_line":"The property of heat exists in all things, but a power is needed for that heat to be made manifest. In the realm of religion, it is the power of Baha'u'llah that causes the heat of the love of God","first_line_orig":"حرارت در جمیع اشیا موجود است اما قوه ای لازم که آن را ظاهر کند همچنین در عالم دیانت   ","language":"3","word_count":"110","subjects":"@power of the Manifestation of God, @teaching the Cause; call to teach, @heat and motion, @John the Baptist","translations":[]}]}
