{"pin":"BB00416","subcodes":[{"code":"BB00416","anchor":"","title":"Fi Mas’alati’l-Bada’ (Letter on the alteration of the Divine Will) (part I)","first_line":"Verily hath begun the fashioning of words in establishing those who dwell in the realms of divine glory [3.5s]","first_line_orig":"بسم الله المنشأ العلیم الذی لا اله الا هو العزیز الحکیم. قد ابتدء باختراع الکلمات فی ثبات اهل السبحات  ","language":"1","word_count":"360","subjects":"@power and sovereignty of God; omnipotence of God, @transcendence; unknowability of God","notes":" \u003ca href=\"https://bahai-library.com/bahailib/1504.pdf#page=69\"\u003eMMAH.057\u003c/a\u003e,  \u003ca href=\"http://www.loomofreality.org/sources/SRC.pdf#page=44\"\u003eSRC.190\u003c/a\u003e,  \u003ca href=\"http://www.loomofreality.org/sources/SRC.pdf#page=46\"\u003eSRC.192x2\u003c/a\u003e","translations":[]}]}
