{"pin":"BH00886","subcodes":[{"code":"BH00886","anchor":"","first_line":"Hallowed praise, sanctified above whatsoever may enter the minds of men, beseemeth the most holy and exalted court of the All-Possessing, the Most High [3.5s]... ...O Abu'l Hasan: May my Glory rest upon thee! Fix thy gaze upon the glory of the Cause. Speak forth that which will attract the hearts and the minds. To demand the Huquq is in no wise permissible… O Amín! Upon thee be My glory. It behoveth thee to have the utmost regard for the dignity of the Cause of God in all circumstances","first_line_orig":"حمد مقدس عما یخطر بالبال بساط امنع اقدس حضرت غنی متعالی را لایق و سزاست  ","language":"5","word_count":"920","subjects":"@prayers (general or uncategorized), @praise and encouragement, @law of Huququ'llah, @steadfastness; perseverance; faithfulness, @power and sovereignty of God; omnipotence of God","translations":[]}]}
