{"pin":"BH00863","subcodes":[{"code":"BH00863","anchor":"","first_line":"Hallowed praise be sanctified above the affairs of the world and the intimations of nations, beyond the doubts of the assailants and the clamor of the deniers [3.5s]","first_line_orig":"حمد مقدس از شئونات عالم و اشارات امم و شبهات معتدین و ضوضاء معرضین ساحت امنع  ","language":"5","word_count":"5160","subjects":"@rejection, opposition and persecution, @expressions of grief; lamentation; sadness, @praise and encouragement, @steadfastness; perseverance; faithfulness, @power and sovereignty of God; omnipotence of God","translations":[]}]}
