{"pin":"BH01661","subcodes":[{"code":"BH01661","anchor":"","first_line":"The Purpose of all beings hath, on this blessed night of the month of Ramadan, willed to speak in the luminous tongue [3.5s]","first_line_orig":"مقصود عالمیان در این شب مبارک ماه رمضان اراده فرموده بلغت نوراء  ","language":"3","word_count":"530","subjects":"@teaching the Cause; call to teach, @the Word of God; influence and centrality of, @steadfastness; perseverance; faithfulness, @rejection, opposition and persecution, @service to others; to the Cause of God, @walking the spiritual path; spiritual wayfaring; the virtuous life","translations":[]}]}
