{"pin":"BH02493","subcodes":[{"code":"BH02493","anchor":"","first_line":"O Ahmad! Upon thee be My glory and My loving-kindness! On this day doth Sinai exult and pride itself, inasmuch as it hath witnessed the advent of its Interlocutor [3.5s]","first_line_orig":"یا احمد علیک بهائی و عنایتی امروز طور میبالد و فخر مینماید چه که بظهور مکلمش  ","language":"5","word_count":"360","subjects":"@trust and reliance in God; turning to Him at all times, @piety; righteousness; fear of God [taqwa], @power and sovereignty of God; omnipotence of God, @wisdom [hikmat]","translations":[]}]}
