{"pin":"BH03230","subcodes":[{"code":"BH03230","anchor":"","title":"Rashh-i-'Ama","first_line":"Tis from our rapture that the clouds of realms above are raining down; ’Tis from Our anthem that the mysteries of faith are raining down","first_line_orig":"رشح عما از جذبه ما میریزد سر وفا از نغمه ما میریزد از باد صبا مشک خطا گشته  ","language":"3","word_count":"280","subjects":"@symbolism, @poems and quotation from poetry, @mystical themes, @Manifestation of God speaking in the voice of Divinity","notes":" \u003ca href=\"https://d9263461.github.io/cl/Baha'i/Others/ROB/V1/Contents.html\"\u003eROB1.045\u003c/a\u003e,  \u003ca href=\"https://bahai-library.com/bahailib/1504.pdf#page=89\"\u003eMMAH.077\u003c/a\u003e,  \u003ca href=\"http://web.archive.org/web/20070930181707/http://bahai-library.com/resources/leiden.list/leiden.list.html#275\"\u003eLL#275\u003c/a\u003e","translations":[]}]}
