{"pin":"BH03636","subcodes":[{"code":"BH03636","anchor":"","title":"Lawh-i-Jawhar-i-Hamd II","first_line":"The essence of praise and its purest expression befitteth that Sovereign, before Whom the monarchs of the world glory in their servitude [3.5s]","first_line_orig":"جوهر حمد و ساذج آن مالکی را لایق و سزاست که ملوک عالم بمملوکیتش فخر نموده و  ","language":"5","word_count":"12200","subjects":"@collection; ordering of the Sacred Writings, @tests and trials; sacrifice and suffering, @steadfastness; perseverance; faithfulness, @service to others; to the Cause of God, @praise and encouragement, @divine unity [tawhid] and degrees of unity, @justice and wrath of God, @power and sovereignty of God; omnipotence of God, @forgiveness; grace; bounty; mercy; compassion of God","translations":[]}]}
