{"pin":"BH03409","subcodes":[{"code":"BH03409","anchor":"","first_line":"O dwellers of the inhabited realm! Hearken unto the call of your Lord, the All-Forgiving, from the direction of this Manifestation whereby illumination hath shone forth [3.5s]","first_line_orig":"یا اصحاب المعمور ان استمعوا ندآء ربکم الغفور من شطر هذا الظهور الذی به اضاء  ","language":"1","word_count":"270","subjects":"@praise and encouragement, @spiritual transformation, @steadfastness; perseverance; faithfulness, @rejection, opposition and persecution","translations":[]}]}
