{"pin":"BH05072","subcodes":[{"code":"BH05072","anchor":"","first_line":"Glory be unto Thee, O Lord my God! I testify unto Thy sovereignty and Thine omnipotence, unto Thy oneness and Thine unconstrained authority","first_line_orig":"سبحانک اللهم یا الهی اشهد بسلطنتک و اقتدارک و بوحدانیتک و اختیارک و بانک انت  ","language":"1","word_count":"190","subjects":"@divine grace, bounty, confirmations; spiritual capacity, @acknowledgment of gift; of monetary contribution, @praise and encouragement, @power and sovereignty of God; omnipotence of God, @forgiveness; grace; bounty; mercy; compassion of God, @call to action","translations":[]}]}
