{"pin":"BH09525","subcodes":[{"code":"BH09525","anchor":"","first_line":"The Book of God hath been sent down in truth from the presence of One All-Knowing, All-Wise. Verily, it is the Balance of Justice among all created things and the Sign [3.5s]","first_line_orig":"کتاب الله نزل بالحق تنزیلا من لدن علیم حکیم انه لقسطاس الحق بین الخلق و الایه  ","language":"1","word_count":"100","subjects":"@knowledge; recognition of God, @Word of God is its own standard, @justice and wrath of God, @heedlessness and ignorance of the people","translations":[]}]}
