{"pin":"BH09983","subcodes":[{"code":"BH09983","anchor":"","first_line":"The Book which the Beloved hath sent down, that thereby may be kindled the hearts of them that have cast aside their desires and taken hold of that which they were commanded [3.5s]","first_line_orig":"کتاب انزله المحبوب لیشتعل به قلوب الذین نبذوا اهوائهم و اخذوا ما امروا به من  ","language":"1","word_count":"90","subjects":"@praise and encouragement, @detachment; severance; renunciation; patience, @spiritual prerequisites of teaching the Cause","notes":" \u003ca href=\"https://d9263461.github.io/cl/Baha'i/Others/ROB/V2/Contents.html\"\u003eROB2.179\u003c/a\u003e,  \u003ca href=\"http://web.archive.org/web/20070930181707/http://bahai-library.com/resources/leiden.list/leiden.list.html#2\"\u003eLL#002\u003c/a\u003e","translations":[]}]}
