{"pin":"BH10703","subcodes":[{"code":"BH10703","anchor":"","first_line":"O Heaven of Healing! I beseech Thee, by the Sun of Thy grace, and the Moon of Thy loving-kindness, and the Star of Thy bounty, to prescribe healing [3.5s]","first_line_orig":"یا سماء الشفاء اسئلک بشمس فضلک و قمر عنایتک و نجم جودک بان تکتب الشفاء من  ","language":"1","word_count":"70","subjects":"@prayer for healing, @Manifestation of God as tree of life; sadratu'l-muntaha, @forgiveness; grace; bounty; mercy; compassion of God, @symbolism of color and light","translations":[]}]}
