{"pin":"BH11748","subcodes":[{"code":"BH11748","anchor":"","first_line":"Praised be God, Who hath adorned the heaven of love with the stars of unity and harmony, and hath ordained that in the world of being marriage be the chief instrument","first_line_orig":"الحمد لله الذی نور العالم بنیر لاح و اشرق من فجر الظهور فی افق سماء بیان الرحمن  ","language":"1","word_count":"280","subjects":"@prayer for married couples, @the Word of God; influence and centrality of, @transcendence; unknowability of God, @unity; oneness of humanity, @Manifestation of God speaking in the voice of Divinity","translations":[{"language":"en","lang_name":"English"}]}]}
