{"pin":"BH11774","subcodes":[{"code":"BH11774","anchor":"","first_line":"Glorified be He Who sendeth down verses as He willeth, whereby certain servants go astray while others are guided! Ever hath He been [3.5s]","first_line_orig":"فسبحان الذی ینزل الایات کیف یشاء یضل منها عباد و یهتدی آخرون لم یزل کان  ","language":"1","word_count":"196","subjects":"@being a source of light; guidance, @thankfulness; gratitude, @power and sovereignty of God; omnipotence of God, @heedlessness and ignorance of the people, @rejection, opposition and persecution, @proclamation of the Cause (general or uncategorized)","translations":[]}]}
