{"pin":"BH11909","subcodes":[{"code":"BH11909","anchor":"","first_line":"O son of Ḥusayn! Give ear unto My call from the direction of the prison and say: Praise be unto Thee, O Lord of all worlds, for having made mention of Me [3.5s]","first_line_orig":"یا ابن حسین اسمع ندائی من شطر السجن و قل لک الحمد یا اله العالمین بما ذکرتنی  ","language":"1","word_count":"50","subjects":"@praise and encouragement, @martyrs and martyrdom, @steadfastness; perseverance; faithfulness","translations":[{"language":"az","lang_name":"Azerbaijani"},{"language":"uk","lang_name":"Ukrainian"}]}]}
