{"pin":"TMP00156","translations":[{"language":"fa","lang_name":"Persian","text":"هواللّه\nالهی گواهی که آرزوی مشاهدۀ انوار کنم و تمنّای ادراکِ اسرار، از بیگانگی بیزار نما و به یگانگی خویش آشنا و کامکار فرما، غمخوارم  غمگساری کن، خاکسارم بزرگواری نما، یزدان مهربانم توئی، بخششی بخش که رُخَم تابنده و درخشنده گردد و زندگیِ پاینده میسّر شود."},{"language":"fa-translit","lang_name":"Persian (Latin)","text":"Húva'lláh\nIláhí guváhí kih árzú-yi musháhadih-yi anvár kunam va tamanná-yi idrák-i asrár, az bígánagí bízár namá va bih yagánagí-yi khvísh áshná va kámpkár farmá, ghamkhváram ghamgusárí kun, kháksáram buzurgvārí namá, Yazdán-i mihrabánam tú'í, bakhshishí bakhsh kih rukhám tábandih va darakhshandih gardad va zindigí-yi páyandih muyassar shavad."}]}
